Workbook

Sheet orders
A1: Order ID | B1: Order Date | C1: Ship Date | D1: Ship Mode | E1: Customer ID | F1: Product ID | G1: Sales | H1: Quantity | I1: Discount | J1: Profit
A2: CA-2016-152156 | B2: 42682 | C2: 42685 | D2: Second Class | E2: CG-12520 | F2: FUR-BO-10001798 | G2: 261.96 | H2: 2 | I2: 0 | J2: 41.9136
A3: CA-2016-152156 | B3: 42682 | C3: 42685 | D3: Second Class | E3: CG-12520 | F3: FUR-CH-10000454 | G3: 731.94 | H3: 3 | I3: 0 | J3: 219.582
A4: CA-2016-138688 | B4: 42533 | C4: 42537 | D4: Second Class | E4: DV-13045 | F4: OFF-LA-10000240 | G4: 14.62 | H4: 2 | I4: 0 | J4: 6.8714
A5: US-2015-108966 | B5: 42288 | C5: 42295 | D5: Standard Class | E5: SO-20335 | F5: FUR-TA-10000577 | G5: 957.5775 | H5: 5 | I5: 0.45 | J5: -383.031
A6: US-2015-108966 | B6: 42288 | C6: 42295 | D6: Standard Class | E6: SO-20335 | F6: OFF-ST-10000760 | G6: 22.368 | H6: 2 | I6: 0.2 | J6: 2.5164
A7: CA-2014-115812 | B7: 41799 | C7: 41804 | D7: Standard Class | E7: BH-11710 | F7: FUR-FU-10001487 | G7: 48.86 | H7: 7 | I7: 0 | J7: 14.1694
A8: CA-2014-115812 | B8: 41799 | C8: 41804 | D8: Standard Class | E8: BH-11710 | F8: OFF-AR-10002833 | G8: 7.28 | H8: 4 | I8: 0 | J8: 1.9656
A9: CA-2014-115812 | B9: 41799 | C9: 41804 | D9: Standard Class | E9: BH-11710 | F9: TEC-PH-10002275 | G9: 907.152 | H9: 6 | I9: 0.2 | J9: 90.7152
A10: CA-2014-115812 | B10: 41799 | C10: 41804 | D10: Standard Class | E10: BH-11710 | F10: OFF-BI-10003910 | G10: 18.504 | H10: 3 | I10: 0.2 | J10: 5.7825
A11: CA-2014-115812 | B11: 41799 | C11: 41804 | D11: Standard Class | E11: BH-11710 | F11: OFF-AP-10002892 | G11: 114.9 | H11: 5 | I11: 0 | J11: 34.47
A12: CA-2014-115812 | B12: 41799 | C12: 41804 | D12: Standard Class | E12: BH-11710 | F12: FUR-TA-10001539 | G12: 1706.184 | H12: 9 | I12: 0.2 | J12: 85.3092
A13: CA-2014-115812 | B13: 41799 | C13: 41804 | D13: Standard Class | E13: BH-11710 | F13: TEC-PH-10002033 | G13: 911.424 | H13: 4 | I13: 0.2 | J13: 68.3568
... A9995: CA-2017-119914 | B9995: 42859 | C9995: 42864 | D9995: Second Class | E9995: CC-12220 | F9995: OFF-AP-10002684 | G9995: 243.16 | H9995: 2 | I9995: 0 | J9995: 72.948

Sheet product
A1: Product ID | B1: Category | C1: Sub-Category | D1: Product Name
A2: FUR-BO-10001798 | B2: Furniture | C2: Bookcases | D2: Bush Somerset Collection Bookcase
A3: FUR-CH-10000454 | B3: Furniture | C3: Chairs | D3: Hon Deluxe Fabric Upholstered Stacking Chairs, Rounded Back
A4: OFF-LA-10000240 | B4: Office Supplies | C4: Labels | D4: Self-Adhesive Address Labels for Typewriters by Universal
A5: FUR-TA-10000577 | B5: Furniture | C5: Tables | D5: Bretford CR4500 Series Slim Rectangular Table
A6: OFF-ST-10000760 | B6: Office Supplies | C6: Storage | D6: Eldon Fold 'N Roll Cart System
A7: FUR-FU-10001487 | B7: Furniture | C7: Furnishings | D7: Eldon Expressions Wood and Plastic Desk Accessories, Cherry Wood
A8: OFF-AR-10002833 | B8: Office Supplies | C8: Art | D8: Newell 322
A9: TEC-PH-10002275 | B9: Technology | C9: Phones | D9: Mitel 5320 IP Phone VoIP phone
A10: OFF-BI-10003910 | B10: Office Supplies | C10: Binders | D10: DXL Angle-View Binders with Locking Rings by Samsill
A11: OFF-AP-10002892 | B11: Office Supplies | C11: Appliances | D11: Belkin F5C206VTEL 6 Outlet Surge
A12: FUR-TA-10001539 | B12: Furniture | C12: Tables | D12: Chromcraft Rectangular Conference Tables
... A1863: OFF-ST-10001627 | B1863: Office Supplies | C1863: Storage | D1863: Eldon Jumbo ProFile Portable File Boxes Graphite/Black

Sheet customers
A1: Customer ID | B1: Customer Name | C1: Segment
A2: CG-12520 | B2: Claire Gute | C2: Consumer
A3: DV-13045 | B3: Darrin Van Huff | C3: Corporate
A4: SO-20335 | B4: Sean O'Donnell | C4: Consumer
A5: BH-11710 | B5: Brosina Hoffman | C5: Consumer
A6: AA-10480 | B6: Andrew Allen | C6: Consumer
A7: IM-15070 | B7: Irene Maddox | C7: Consumer
A8: HP-14815 | B8: Harold Pawlan | C8: Home Office
A9: PK-19075 | B9: Pete Kriz | C9: Consumer
A10: AG-10270 | B10: Alejandro Grove | C10: Consumer
A11: ZD-21925 | B11: Zuschuss Donatelli | C11: Consumer
A12: KB-16585 | B12: Ken Black | C12: Corporate
... A794: SM-20905 | B794: Susan MacKendrick | C794: Consumer

Sheet TABELA TOTAL
A1: Order ID | B1: Order Date | C1: Ship Date | D1: Ship Mode | E1: Customer ID | F1: Product ID | G1: Sales | H1: Quantity | I1: Discount | J1: Profit | K1: Category | L1: Sub-Category | M1: Product Name
A2: CA-2017-126221 | B2: 43099 | C2: 43105 | D2: Standard Class | E2: CC-12430 | F2: OFF-AP-10002457 | G2: 209.3 | H2: 2 | I2: 0 | J2: 56.511 | K2: =INDEX(product!B:B,MATCH('TABELA TOTAL'!$F647,product!A:A,0)) -> Office Supplies | L2: =INDEX(product!C:C,MATCH(F2,product!A:A,)) -> Appliances | M2: =INDEX(product!D:D,MATCH(F2,product!A:A,)) -> Eureka The Boss Plus 12-Amp Hard Box Upright Vacuum, Red
A3: CA-2017-143259 | B3: 43099 | C3: 43103 | D3: Standard Class | E3: PO-18865 | F3: FUR-BO-10003441 | G3: 323.136 | H3: 4 | I3: 0.2 | J3: 12.1176 | K3: =INDEX(product!B:B,MATCH('TABELA TOTAL'!$F908,product!A:A,0)) -> Office Supplies | L3: =INDEX(product!C:C,MATCH(F3,product!A:A,)) -> Bookcases | M3: =INDEX(product!D:D,MATCH(F3,product!A:A,)) -> Bush Westfield Collection Bookcases, Fully Assembled
A4: CA-2017-143259 | B4: 43099 | C4: 43103 | D4: Standard Class | E4: PO-18865 | F4: TEC-PH-10004774 | G4: 90.93 | H4: 7 | I4: 0 | J4: 2.7279 | K4: =INDEX(product!B:B,MATCH('TABELA TOTAL'!$F909,product!A:A,0)) -> Office Supplies | L4: =INDEX(product!C:C,MATCH(F4,product!A:A,)) -> Phones | M4: =INDEX(product!D:D,MATCH(F4,product!A:A,)) -> Gear Head AU3700S Headset
A5: CA-2017-143259 | B5: 43099 | C5: 43103 | D5: Standard Class | E5: PO-18865 | F5: OFF-BI-10003684 | G5: 52.776 | H5: 3 | I5: 0.2 | J5: 19.791 | K5: =INDEX(product!B:B,MATCH('TABELA TOTAL'!$F910,product!A:A,0)) -> Technology | L5: =INDEX(product!C:C,MATCH(F5,product!A:A,)) -> Binders | M5: =INDEX(product!D:D,MATCH(F5,product!A:A,)) -> Wilson Jones Legal Size Ring Binders
A6: CA-2017-115427 | B6: 43099 | C6: 43103 | D6: Standard Class | E6: EB-13975 | F6: OFF-BI-10002103 | G6: 13.904 | H6: 2 | I6: 0.2 | J6: 4.5188 | K6: =INDEX(product!B:B,MATCH('TABELA TOTAL'!$F1298,product!A:A,0)) -> Office Supplies | L6: =INDEX(product!C:C,MATCH(F6,product!A:A,)) -> Binders | M6: =INDEX(product!D:D,MATCH(F6,product!A:A,)) -> Cardinal Slant-D Ring Binder, Heavy Gauge Vinyl
A7: CA-2017-115427 | B7: 43099 | C7: 43103 | D7: Standard Class | E7: EB-13975 | F7: OFF-BI-10004632 | G7: 20.72 | H7: 2 | I7: 0.2 | J7: 6.475 | K7: =INDEX(product!B:B,MATCH('TABELA TOTAL'!$F1299,product!A:A,0)) -> Office Supplies | L7: =INDEX(product!C:C,MATCH(F7,product!A:A,)) -> Binders | M7: =INDEX(product!D:D,MATCH(F7,product!A:A,)) -> Ibico Hi-Tech Manual Binding System
A8: CA-2017-156720 | B8: 43099 | C8: 43103 | D8: Standard Class | E8: JM-15580 | F8: OFF-FA-10003472 | G8: 3.024 | H8: 3 | I8: 0.2 | J8: -0.6048 | K8: =INDEX(product!B:B,MATCH('TABELA TOTAL'!$F5093,product!A:A,0)) -> Office Supplies | L8: =INDEX(product!C:C,MATCH(F8,product!A:A,)) -> Fasteners | M8: =INDEX(product!D:D,MATCH(F8,product!A:A,)) -> Bagged Rubber Bands
A9: CA-2017-118885 | B9: 43098 | C9: 43102 | D9: Standard Class | E9: JG-15160 | F9: FUR-CH-10002880 | G9: 393.568 | H9: 4 | I9: 0.2 | J9: -44.2764 | K9: =INDEX(product!B:B,MATCH('TABELA TOTAL'!$F1879,product!A:A,0)) -> Office Supplies | L9: =INDEX(product!C:C,MATCH(F9,product!A:A,)) -> Chairs | M9: =INDEX(product!D:D,MATCH(F9,product!A:A,)) -> Global High-Back Leather Tilter, Burgundy
A10: CA-2017-118885 | B10: 43098 | C10: 43102 | D10: Standard Class | E10: JG-15160 | F10: TEC-PH-10002563 | G10: 302.376 | H10: 3 | I10: 0.2 | J10: 22.6782 | K10: =INDEX(product!B:B,MATCH('TABELA TOTAL'!$F1880,product!A:A,0)) -> Technology | L10: =INDEX(product!C:C,MATCH(F10,product!A:A,)) -> Phones | M10: =INDEX(product!D:D,MATCH(F10,product!A:A,)) -> Adtran 1202752G1
A11: US-2017-102638 | B11: 43098 | C11: 43100 | D11: First Class | E11: MC-17845 | F11: OFF-FA-10002988 | G11: 6.03 | H11: 3 | I11: 0 | J11: 2.9547 | K11: =INDEX(product!B:B,MATCH('TABELA TOTAL'!$F2876,product!A:A,0)) -> Office Supplies | L11: =INDEX(product!C:C,MATCH(F11,product!A:A,)) -> Fasteners | M11: =INDEX(product!D:D,MATCH(F11,product!A:A,)) -> Ideal Clamps
A12: CA-2017-158673 | B12: 43098 | C12: 43104 | D12: Standard Class | E12: KB-16600 | F12: OFF-PA-10000994 | G12: 209.7 | H12: 2 | I12: 0 | J12: 100.656 | K12: =INDEX(product!B:B,MATCH('TABELA TOTAL'!$F4241,product!A:A,0)) -> Office Supplies | L12: =INDEX(product!C:C,MATCH(F12,product!A:A,)) -> Paper | M12: =INDEX(product!D:D,MATCH(F12,product!A:A,)) -> Xerox 1915
A13: CA-2017-146626 | B13: 43098 | C13: 43105 | D13: Standard Class | E13: BP-11185 | F13: FUR-FU-10002501 | G13: 101.12 | H13: 8 | I13: 0 | J13: 37.4144 | K13: =INDEX(product!B:B,MATCH('TABELA TOTAL'!$F5133,product!A:A,0)) -> Technology | L13: =INDEX(product!C:C,MATCH(F13,product!A:A,)) -> Furnishings | M13: =INDEX(product!D:D,MATCH(F13,product!A:A,)) -> Nu-Dell Executive Frame
A14: CA-2017-130631 | B14: 43098 | C14: 43102 | D14: Standard Class | E14: BS-11755 | F14: OFF-FA-10000089 | G14: 19.6 | H14: 5 | I14: 0 | J14: 9.604 | K14: =INDEX(product!B:B,MATCH('TABELA TOTAL'!$F5458,product!A:A,0)) -> Furniture | L14: =INDEX(product!C:C,MATCH(F14,product!A:A,)) -> Fasteners | M14: =INDEX(product!D:D,MATCH(F14,product!A:A,)) -> Acco Glide Clips
A15: CA-2017-130631 | B15: 43098 | C15: 43102 | D15: Standard Class | E15: BS-11755 | F15: FUR-FU-10004093 | G15: 68.46 | H15: 2 | I15: 0 | J15: 20.538 | K15: =INDEX(product!B:B,MATCH('TABELA TOTAL'!$F5459,product!A:A,0)) -> Office Supplies | L15: =INDEX(product!C:C,MATCH(F15,product!A:A,)) -> Furnishings | M15: =INDEX(product!D:D,MATCH(F15,product!A:A,)) -> Hand-Finished Solid Wood Document Frame
A16: US-2017-158526 | B16: 43098 | C16: 43101 | D16: Second Class | E16: KH-16360 | F16: FUR-CH-10002602 | G16: 1207.84 | H16: 8 | I16: 0 | J16: 314.0384 | K16: =INDEX(product!B:B,MATCH('TABELA TOTAL'!$F7634,product!A:A,0)) -> Office Supplies | L16: =INDEX(product!C:C,MATCH(F16,product!A:A,)) -> Chairs | M16: =INDEX(product!D:D,MATCH(F16,product!A:A,)) -> DMI Arturo Collection Mission-style Design Wood Chair
A17: US-2017-158526 | B17: 43098 | C17: 43101 | D17: Second Class | E17: KH-16360 | F17: OFF-BI-10002414 | G17: 12.53 | H17: 1 | I17: 0 | J17: 5.8891 | K17: =INDEX(product!B:B,MATCH('TABELA TOTAL'!$F7635,product!A:A,0)) -> Office Supplies | L17: =INDEX(product!C:C,MATCH(F17,product!A:A,)) -> Binders | M17: =INDEX(product!D:D,MATCH(F17,product!A:A,)) -> GBC ProClick Spines for 32-Hole Punch
A18: US-2017-158526 | B18: 43098 | C18: 43101 | D18: Second Class | E18: KH-16360 | F18: OFF-AR-10003696 | G18: 34.58 | H18: 1 | I18: 0 | J18: 10.0282 | K18: =INDEX(product!B:B,MATCH('TABELA TOTAL'!$F7636,product!A:A,0)) -> Furniture | L18: =INDEX(product!C:C,MATCH(F18,product!A:A,)) -> Art | M18: =INDEX(product!D:D,MATCH(F18,product!A:A,)) -> Panasonic KP-350BK Electric Pencil Sharpener with Auto Stop
A19: US-2017-158526 | B19: 43098 | C19: 43101 | D19: Second Class | E19: KH-16360 | F19: FUR-CH-10004495 | G19: 300.98 | H19: 1 | I19: 0 | J19: 87.2842 | K19: =INDEX(product!B:B,MATCH('TABELA TOTAL'!$F7637,product!A:A,0)) -> Furniture | L19: =INDEX(product!C:C,MATCH(F19,product!A:A,)) -> Chairs | M19: =INDEX(product!D:D,MATCH(F19,product!A:A,)) -> Global Leather and Oak Executive Chair, Black
A20: US-2017-158526 | B20: 43098 | C20: 43101 | D20: Second Class | E20: KH-16360 | F20: FUR-CH-10001270 | G20: 258.75 | H20: 3 | I20: 0 | J20: 77.625 | K20: =INDEX(product!B:B,MATCH('TABELA TOTAL'!$F7638,product!A:A,0)) -> Technology | L20: =INDEX(product!C:C,MATCH(F20,product!A:A,)) -> Chairs | M20: =INDEX(product!D:D,MATCH(F20,product!A:A,)) -> Harbour Creations Steel Folding Chair
A21: CA-2017-163979 | B21: 43097 | C21: 43102 | D21: Second Class | E21: KH-16690 | F21: OFF-ST-10003208 | G21: 725.84 | H21: 4 | I21: 0 | J21: 210.4936 | K21: =INDEX(product!B:B,MATCH('TABELA TOTAL'!$F272,product!A:A,0)) -> Furniture | L21: =INDEX(product!C:C,MATCH(F21,product!A:A,)) -> Storage | M21: =INDEX(product!D:D,MATCH(F21,product!A:A,)) -> Adjustable Depth Letter/Legal Cart
A22: CA-2017-164826 | B22: 43097 | C22: 43104 | D22: Standard Class | E22: JF-15415 | F22: OFF-LA-10001297 | G22: 72.45 | H22: 7 | I22: 0 | J22: 34.776 | K22: =INDEX(product!B:B,MATCH('TABELA TOTAL'!$F572,product!A:A,0)) -> Office Supplies | L22: =INDEX(product!C:C,MATCH(F22,product!A:A,)) -> Labels | M22: =INDEX(product!D:D,MATCH(F22,product!A:A,)) -> Avery 473
A23: CA-2017-164826 | B23: 43097 | C23: 43104 | D23: Standard Class | E23: JF-15415 | F23: OFF-FA-10000585 | G23: 13.96 | H23: 4 | I23: 0 | J23: 6.4216 | K23: =INDEX(product!B:B,MATCH('TABELA TOTAL'!$F573,product!A:A,0)) -> Office Supplies | L23: =INDEX(product!C:C,MATCH(F23,product!A:A,)) -> Fasteners | M23: =INDEX(product!D:D,MATCH(F23,product!A:A,)) -> OIC Bulk Pack Metal Binder Clips
A24: CA-2017-164826 | B24: 43097 | C24: 43104 | D24: Standard Class | E24: JF-15415 | F24: OFF-BI-10001922 | G24: 33.264 | H24: 7 | I24: 0.2 | J24: 11.2266 | K24: =INDEX(product!B:B,MATCH('TABELA TOTAL'!$F574,product!A:A,0)) -> Office Supplies | L24: =INDEX(product!C:C,MATCH(F24,product!A:A,)) -> Binders | M24: =INDEX(product!D:D,MATCH(F24,product!A:A,)) -> Storex Dura Pro Binders
A25: CA-2017-164826 | B25: 43097 | C25: 43104 | D25: Standard Class | E25: JF-15415 | F25: TEC-PH-10000347 | G25: 14.85 | H25: 3 | I25: 0 | J25: 4.0095 | K25: =INDEX(product!B:B,MATCH('TABELA TOTAL'!$F575,product!A:A,0)) -> Furniture | L25: =INDEX(product!C:C,MATCH(F25,product!A:A,)) -> Phones | M25: =INDEX(product!D:D,MATCH(F25,product!A:A,)) -> Cush Cases Heavy Duty Rugged Cover Case for Samsung Galaxy S5 - Purple
A26: CA-2017-136539 | B26: 43097 | C26: 43101 | D26: Standard Class | E26: GH-14665 | F26: OFF-AR-10001958 | G26: 27.168 | H26: 2 | I26: 0.2 | J26: 2.7168 | K26: =INDEX(product!B:B,MATCH('TABELA TOTAL'!$F955,product!A:A,0)) -> Office Supplies | L26: =INDEX(product!C:C,MATCH(F26,product!A:A,)) -> Art | M26: =INDEX(product!D:D,MATCH(F26,product!A:A,)) -> Stanley Bostitch Contemporary Electric Pencil Sharpeners
A27: CA-2017-136539 | B27: 43097 | C27: 43101 | D27: Standard Class | E27: GH-14665 | F27: FUR-BO-10004709 | G27: 78.8528 | H27: 2 | I27: 0.32 | J27: -11.596 | K27: =INDEX(product!B:B,MATCH('TABELA TOTAL'!$F956,product!A:A,0)) -> Office Supplies | L27: =INDEX(product!C:C,MATCH(F27,product!A:A,)) -> Bookcases | M27: =INDEX(product!D:D,MATCH(F27,product!A:A,)) -> Bush Westfield Collection Bookcases, Medium Cherry Finish
A28: CA-2017-129805 | B28: 43097 | C28: 43102 | D28: Standard Class | E28: HM-14860 | F28: FUR-FU-10001935 | G28: 7.4 | H28: 2 | I28: 0 | J28: 3.034 | K28: =INDEX(product!B:B,MATCH('TABELA TOTAL'!$F2433,product!A:A,0)) -> Office Supplies | L28: =INDEX(product!C:C,MATCH(F28,product!A:A,)) -> Furnishings | M28: =INDEX(product!D:D,MATCH(F28,product!A:A,)) -> 3M Hangers With Command Adhesive
A29: CA-2017-127516 | B29: 43097 | C29: 43103 | D29: Standard Class | E29: EH-14005 | F29: OFF-ST-10000736 | G29: 64.784 | H29: 1 | I29: 0.2 | J29: -12.9568 | K29: =INDEX(product!B:B,MATCH('TABELA TOTAL'!$F4289,product!A:A,0)) -> Office Supplies | L29: =INDEX(product!C:C,MATCH(F29,product!A:A,)) -> Storage | M29: =INDEX(product!D:D,MATCH(F29,product!A:A,)) -> Carina Double Wide Media Storage Towers in Natural & Black
A30: US-2017-162068 | B30: 43097 | C30: 43100 | D30: Second Class | E30: PC-18745 | F30: OFF-BI-10002813 | G30: 1.188 | H30: 2 | I30: 0.7 | J30: -0.99 | K30: =INDEX(product!B:B,MATCH('TABELA TOTAL'!$F6091,product!A:A,0)) -> Office Supplies | L30: =INDEX(product!C:C,MATCH(F30,product!A:A,)) -> Binders | M30: =INDEX(product!D:D,MATCH(F30,product!A:A,)) -> Avery Reinforcements for Hole-Punch Pages
A31: CA-2017-101322 | B31: 43097 | C31: 43100 | D31: First Class | E31: JG-15310 | F31: FUR-CH-10003968 | G31: 340.704 | H31: 6 | I31: 0.2 | J31: -34.0704 | K31: =INDEX(product!B:B,MATCH('TABELA TOTAL'!$F6151,product!A:A,0)) -> Office Supplies | L31: =INDEX(product!C:C,MATCH(F31,product!A:A,)) -> Chairs | M31: =INDEX(product!D:D,MATCH(F31,product!A:A,)) -> Novimex Turbo Task Chair
A32: CA-2017-163860 | B32: 43097 | C32: 43101 | D32: Standard Class | E32: LO-17170 | F32: OFF-BI-10003784 | G32: 1.68 | H32: 5 | I32: 0.8 | J32: -2.688 | K32: =INDEX(product!B:B,MATCH('TABELA TOTAL'!$F6820,product!A:A,0)) -> Office Supplies | L32: =INDEX(product!C:C,MATCH(F32,product!A:A,)) -> Binders | M32: =INDEX(product!D:D,MATCH(F32,product!A:A,)) -> Computer Printout Index Tabs
A33: CA-2017-163860 | B33: 43097 | C33: 43101 | D33: Standard Class | E33: LO-17170 | F33: FUR-FU-10004586 | G33: 7.968 | H33: 3 | I33: 0.6 | J33: -2.3904 | K33: =INDEX(product!B:B,MATCH('TABELA TOTAL'!$F6821,product!A:A,0)) -> Office Supplies | L33: =INDEX(product!C:C,MATCH(F33,product!A:A,)) -> Furnishings | M33: =INDEX(product!D:D,MATCH(F33,product!A:A,)) -> G.E. Longer-Life Indoor Recessed Floodlight Bulbs
A34: CA-2017-163860 | B34: 43097 | C34: 43101 | D34: Standard Class | E34: LO-17170 | F34: FUR-CH-10004698 | G34: 113.372 | H34: 2 | I34: 0.3 | J34: -3.2392 | K34: =INDEX(product!B:B,MATCH('TABELA TOTAL'!$F6822,product!A:A,0)) -> Office Supplies | L34: =INDEX(product!C:C,MATCH(F34,product!A:A,)) -> Chairs | M34: =INDEX(product!D:D,MATCH(F34,product!A:A,)) -> Padded Folding Chairs, Black, 4/Carton
A35: CA-2017-163860 | B35: 43097 | C35: 43101 | D35: Standard Class | E35: LO-17170 | F35: FUR-FU-10001935 | G35: 2.96 | H35: 2 | I35: 0.6 | J35: -1.406 | K35: =INDEX(product!B:B,MATCH('TABELA TOTAL'!$F6823,product!A:A,0)) -> Office Supplies | L35: =INDEX(product!C:C,MATCH(F35,product!A:A,)) -> Furnishings | M35: =INDEX(product!D:D,MATCH(F35,product!A:A,)) -> 3M Hangers With Command Adhesive
A36: CA-2017-135111 | B36: 43097 | C36: 43102 | D36: Standard Class | E36: CS-12400 | F36: OFF-AR-10004707 | G36: 2.48 | H36: 1 | I36: 0 | J36: 0.868 | K36: =INDEX(product!B:B,MATCH('TABELA TOTAL'!$F7486,product!A:A,0)) -> Office Supplies | L36: =INDEX(product!C:C,MATCH(F36,product!A:A,)) -> Art | M36: =INDEX(product!D:D,MATCH(F36,product!A:A,)) -> Staples in misc. colors
A37: CA-2017-135111 | B37: 43097 | C37: 43102 | D37: Standard Class | E37: CS-12400 | F37: OFF-BI-10004040 | G37: 25.9 | H37: 5 | I37: 0 | J37: 12.691 | K37: =INDEX(product!B:B,MATCH('TABELA TOTAL'!$F7487,product!A:A,0)) -> Technology | L37: =INDEX(product!C:C,MATCH(F37,product!A:A,)) -> Binders | M37: =INDEX(product!D:D,MATCH(F37,product!A:A,)) -> Wilson Jones Impact Binders
A38: CA-2017-122798 | B38: 43097 | C38: 43101 | D38: Standard Class | E38: SV-20935 | F38: OFF-ST-10003058 | G38: 118.25 | H38: 5 | I38: 0 | J38: 34.2925 | K38: =INDEX(product!B:B,MATCH('TABELA TOTAL'!$F8099,product!A:A,0)) -> Furniture | L38: =INDEX(product!C:C,MATCH(F38,product!A:A,)) -> Storage | M38: =INDEX(product!D:D,MATCH(F38,product!A:A,)) -> Eldon Mobile Mega Data Cart Mega Stackable Add-On Trays
A39: CA-2017-122798 | B39: 43097 | C39: 43101 | D39: Standard Class | E39: SV-20935 | F39: OFF-PA-10004239 | G39: 4.28 | H39: 1 | I39: 0 | J39: 1.926 | K39: =INDEX(product!B:B,MATCH('TABELA TOTAL'!$F8100,product!A:A,0)) -> Office Supplies | L39: =INDEX(product!C:C,MATCH(F39,product!A:A,)) -> Paper | M39: =INDEX(product!D:D,MATCH(F39,product!A:A,)) -> Xerox 1953
A40: CA-2017-134404 | B40: 43096 | C40: 43096 | D40: Same Day | E40: DR-12880 | F40: TEC-PH-10000576 | G40: 164.388 | H40: 2 | I40: 0.4 | J40: -35.6174 | K40: =INDEX(product!B:B,MATCH('TABELA TOTAL'!$F2571,product!A:A,0)) -> Office Supplies | L40: =INDEX(product!C:C,MATCH(F40,product!A:A,)) -> Phones | M40: =INDEX(product!D:D,MATCH(F40,product!A:A,)) -> AT&T 1080 Corded phone
A41: CA-2017-134404 | B41: 43096 | C41: 43096 | D41: Same Day | E41: DR-12880 | F41: OFF-AR-10004441 | G41: 13.248 | H41: 4 | I41: 0.2 | J41: 3.6432 | K41: =INDEX(product!B:B,MATCH('TABELA TOTAL'!$F2572,product!A:A,0)) -> Office Supplies | L41: =INDEX(product!C:C,MATCH(F41,product!A:A,)) -> Art | M41: =INDEX(product!D:D,MATCH(F41,product!A:A,)) -> BIC Brite Liner Highlighters
A42: US-2017-106705 | B42: 43095 | C42: 43101 | D42: Standard Class | E42: PO-18850 | F42: OFF-PA-10001509 | G42: 44.75 | H42: 5 | I42: 0 | J42: 20.585 | K42: =INDEX(product!B:B,MATCH('TABELA TOTAL'!$F1010,product!A:A,0)) -> Technology | L42: =INDEX(product!C:C,MATCH(F42,product!A:A,)) -> Paper | M42: =INDEX(product!D:D,MATCH(F42,product!A:A,)) -> Recycled Desk Saver Line "While You Were Out" Book, 5 1/2" X 4"
A43: CA-2017-112487 | B43: 43095 | C43: 43099 | D43: Standard Class | E43: TC-21535 | F43: OFF-BI-10000494 | G43: 3.132 | H43: 2 | I43: 0.7 | J43: -2.61 | K43: =INDEX(product!B:B,MATCH('TABELA TOTAL'!$F3787,product!A:A,0)) -> Furniture | L43: =INDEX(product!C:C,MATCH(F43,product!A:A,)) -> Binders | M43: =INDEX(product!D:D,MATCH(F43,product!A:A,)) -> Acco Economy Flexible Poly Round Ring Binder
A44: CA-2017-121741 | B44: 43095 | C44: 43095 | D44: Same Day | E44: YC-21895 | F44: OFF-ST-10004459 | G44: 750.68 | H44: 2 | I44: 0 | J44: 37.534 | K44: =INDEX(product!B:B,MATCH('TABELA TOTAL'!$F5476,product!A:A,0)) -> Office Supplies | L44: =INDEX(product!C:C,MATCH(F44,product!A:A,)) -> Storage | M44: =INDEX(product!D:D,MATCH(F44,product!A:A,)) -> Tennsco Single-Tier Lockers
A45: CA-2017-136238 | B45: 43095 | C45: 43101 | D45: Standard Class | E45: KB-16240 | F45: OFF-PA-10004285 | G45: 16.032 | H45: 3 | I45: 0.2 | J45: 5.6112 | K45: =INDEX(product!B:B,MATCH('TABELA TOTAL'!$F8160,product!A:A,0)) -> Office Supplies | L45: =INDEX(product!C:C,MATCH(F45,product!A:A,)) -> Paper | M45: =INDEX(product!D:D,MATCH(F45,product!A:A,)) -> Xerox 1959
A46: CA-2017-146780 | B46: 43094 | C46: 43099 | D46: Standard Class | E46: CV-12805 | F46: FUR-FU-10001934 | G46: 41.96 | H46: 2 | I46: 0 | J46: 10.9096 | K46: =INDEX(product!B:B,MATCH('TABELA TOTAL'!$F112,product!A:A,0)) -> Office Supplies | L46: =INDEX(product!C:C,MATCH(F46,product!A:A,)) -> Furnishings | M46: =INDEX(product!D:D,MATCH(F46,product!A:A,)) -> Magnifier Swing Arm Lamp
A47: CA-2017-161480 | B47: 43094 | C47: 43098 | D47: Standard Class | E47: RA-19285 | F47: FUR-BO-10004015 | G47: 191.984 | H47: 2 | I47: 0.2 | J47: 4.7996 | K47: =INDEX(product!B:B,MATCH('TABELA TOTAL'!$F690,product!A:A,0)) -> Furniture | L47: =INDEX(product!C:C,MATCH(F47,product!A:A,)) -> Bookcases | M47: =INDEX(product!D:D,MATCH(F47,product!A:A,)) -> Bush Andora Bookcase, Maple/Graphite Gray Finish
A48: CA-2017-163510 | B48: 43094 | C48: 43097 | D48: Second Class | E48: JW-15955 | F48: OFF-ST-10000563 | G48: 95.94 | H48: 3 | I48: 0 | J48: 9.594 | K48: =INDEX(product!B:B,MATCH('TABELA TOTAL'!$F2004,product!A:A,0)) -> Office Supplies | L48: =INDEX(product!C:C,MATCH(F48,product!A:A,)) -> Storage | M48: =INDEX(product!D:D,MATCH(F48,product!A:A,)) -> Fellowes Bankers Box Stor/Drawer Steel Plus
A49: CA-2017-163510 | B49: 43094 | C49: 43097 | D49: Second Class | E49: JW-15955 | F49: FUR-CH-10001146 | G49: 304.45 | H49: 5 | I49: 0 | J49: 76.1125 | K49: =INDEX(product!B:B,MATCH('TABELA TOTAL'!$F2005,product!A:A,0)) -> Furniture | L49: =INDEX(product!C:C,MATCH(F49,product!A:A,)) -> Chairs | M49: =INDEX(product!D:D,MATCH(F49,product!A:A,)) -> Global Value Mid-Back Manager's Chair, Gray
A50: US-2017-147669 | B50: 43094 | C50: 43099 | D50: Standard Class | E50: SV-20935 | F50: TEC-AC-10002473 | G50: 158.928 | H50: 7 | I50: 0.2 | J50: 41.7186 | K50: =INDEX(product!B:B,MATCH('TABELA TOTAL'!$F2425,product!A:A,0)) -> Office Supplies | L50: =INDEX(product!C:C,MATCH(F50,product!A:A,)) -> Accessories | M50: =INDEX(product!D:D,MATCH(F50,product!A:A,)) -> Maxell 4.7GB DVD-R
A51: US-2017-147669 | B51: 43094 | C51: 43099 | D51: Standard Class | E51: SV-20935 | F51: OFF-BI-10000632 | G51: 13.023 | H51: 1 | I51: 0.7 | J51: -10.4184 | K51: =INDEX(product!B:B,MATCH('TABELA TOTAL'!$F2426,product!A:A,0)) -> Office Supplies | L51: =INDEX(product!C:C,MATCH(F51,product!A:A,)) -> Binders | M51: =INDEX(product!D:D,MATCH(F51,product!A:A,)) -> Satellite Sectional Post Binders
A52: US-2017-147669 | B52: 43094 | C52: 43099 | D52: Standard Class | E52: SV-20935 | F52: FUR-TA-10002645 | G52: 273.06 | H52: 2 | I52: 0.4 | J52: -104.673 | K52: =INDEX(product!B:B,MATCH('TABELA TOTAL'!$F2427,product!A:A,0)) -> Technology | L52: =INDEX(product!C:C,MATCH(F52,product!A:A,)) -> Tables | M52: =INDEX(product!D:D,MATCH(F52,product!A:A,)) -> Hon Rectangular Conference Tables
A53: US-2017-147669 | B53: 43094 | C53: 43099 | D53: Standard Class | E53: SV-20935 | F53: OFF-FA-10002975 | G53: 39.312 | H53: 13 | I53: 0.2 | J53: 12.7764 | K53: =INDEX(product!B:B,MATCH('TABELA TOTAL'!$F2428,product!A:A,0)) -> Office Supplies | L53: =INDEX(product!C:C,MATCH(F53,product!A:A,)) -> Fasteners | M53: =INDEX(product!D:D,MATCH(F53,product!A:A,)) -> Staples
A54: CA-2017-114055 | B54: 43094 | C54: 43098 | D54: Second Class | E54: MH-18115 | F54: OFF-PA-10004381 | G54: 96.08 | H54: 2 | I54: 0 | J54: 46.1184 | K54: =INDEX(product!B:B,MATCH('TABELA TOTAL'!$F4923,product!A:A,0)) -> Technology | L54: =INDEX(product!C:C,MATCH(F54,product!A:A,)) -> Paper | M54: =INDEX(product!D:D,MATCH(F54,product!A:A,)) -> 14-7/8 x 11 Blue Bar Computer Printout Paper
A55: CA-2017-114055 | B55: 43094 | C55: 43098 | D55: Second Class | E55: MH-18115 | F55: OFF-FA-10003059 | G55: 3.62 | H55: 2 | I55: 0 | J55: 1.1946 | K55: =INDEX(product!B:B,MATCH('TABELA TOTAL'!$F4924,product!A:A,0)) -> Office Supplies | L55: =INDEX(product!C:C,MATCH(F55,product!A:A,)) -> Fasteners | M55: =INDEX(product!D:D,MATCH(F55,product!A:A,)) -> Assorted Color Push Pins
A56: CA-2017-114055 | B56: 43094 | C56: 43098 | D56: Second Class | E56: MH-18115 | F56: OFF-PA-10000994 | G56: 629.1 | H56: 6 | I56: 0 | J56: 301.968 | K56: =INDEX(product!B:B,MATCH('TABELA TOTAL'!$F4925,product!A:A,0)) -> Office Supplies | L56: =INDEX(product!C:C,MATCH(F56,product!A:A,)) -> Paper | M56: =INDEX(product!D:D,MATCH(F56,product!A:A,)) -> Xerox 1915
A57: CA-2017-114055 | B57: 43094 | C57: 43098 | D57: Second Class | E57: MH-18115 | F57: TEC-PH-10002890 | G57: 90.48 | H57: 2 | I57: 0 | J57: 23.5248 | K57: =INDEX(product!B:B,MATCH('TABELA TOTAL'!$F4926,product!A:A,0)) -> Office Supplies | L57: =INDEX(product!C:C,MATCH(F57,product!A:A,)) -> Phones | M57: =INDEX(product!D:D,MATCH(F57,product!A:A,)) -> AT&T 17929 Lendline Telephone
A58: CA-2017-121398 | B58: 43094 | C58: 43098 | D58: Standard Class | E58: FH-14365 | F58: OFF-BI-10001718 | G58: 153.552 | H58: 3 | I58: 0.2 | J58: 51.8238 | K58: =INDEX(product!B:B,MATCH('TABELA TOTAL'!$F6076,product!A:A,0)) -> Office Supplies | L58: =INDEX(product!C:C,MATCH(F58,product!A:A,)) -> Binders | M58: =INDEX(product!D:D,MATCH(F58,product!A:A,)) -> GBC DocuBind P50 Personal Binding Machine
A59: CA-2017-121398 | B59: 43094 | C59: 43098 | D59: Standard Class | E59: FH-14365 | F59: OFF-ST-10002756 | G59: 270.62 | H59: 2 | I59: 0 | J59: 2.7062 | K59: =INDEX(product!B:B,MATCH('TABELA TOTAL'!$F6077,product!A:A,0)) -> Office Supplies | L59: =INDEX(product!C:C,MATCH(F59,product!A:A,)) -> Storage | M59: =INDEX(product!D:D,MATCH(F59,product!A:A,)) -> Tennsco Stur-D-Stor Boltless Shelving, 5 Shelves, 24" Deep, Sand
A60: CA-2017-162880 | B60: 43094 | C60: 43098 | D60: Standard Class | E60: GD-14590 | F60: OFF-BI-10003314 | G60: 3.856 | H60: 1 | I60: 0.2 | J60: 1.3978 | K60: =INDEX(product!B:B,MATCH('TABELA TOTAL'!$F6808,product!A:A,0)) -> Technology | L60: =INDEX(product!C:C,MATCH(F60,product!A:A,)) -> Binders | M60: =INDEX(product!D:D,MATCH(F60,product!A:A,)) -> Tuff Stuff Recycled Round Ring Binders
A61: CA-2017-134194 | B61: 43094 | C61: 43101 | D61: Standard Class | E61: GA-14725 | F61: OFF-BI-10003684 | G61: 39.582 | H61: 9 | I61: 0.8 | J61: -59.373 | K61: =INDEX(product!B:B,MATCH('TABELA TOTAL'!$F7944,product!A:A,0)) -> Furniture | L61: =INDEX(product!C:C,MATCH(F61,product!A:A,)) -> Binders | M61: =INDEX(product!D:D,MATCH(F61,product!A:A,)) -> Wilson Jones Legal Size Ring Binders
A62: CA-2017-134194 | B62: 43094 | C62: 43101 | D62: Standard Class | E62: GA-14725 | F62: OFF-SU-10000946 | G62: 44.688 | H62: 7 | I62: 0.2 | J62: 5.0274 | K62: =INDEX(product!B:B,MATCH('TABELA TOTAL'!$F7945,product!A:A,0)) -> Office Supplies | L62: =INDEX(product!C:C,MATCH(F62,product!A:A,)) -> Supplies | M62: =INDEX(product!D:D,MATCH(F62,product!A:A,)) -> Staple remover
A63: CA-2017-134194 | B63: 43094 | C63: 43101 | D63: Standard Class | E63: GA-14725 | F63: OFF-AR-10001615 | G63: 31.744 | H63: 2 | I63: 0.2 | J63: 2.3808 | K63: =INDEX(product!B:B,MATCH('TABELA TOTAL'!$F7946,product!A:A,0)) -> Furniture | L63: =INDEX(product!C:C,MATCH(F63,product!A:A,)) -> Art | M63: =INDEX(product!D:D,MATCH(F63,product!A:A,)) -> Newell 34
A64: CA-2017-134194 | B64: 43094 | C64: 43101 | D64: Standard Class | E64: GA-14725 | F64: OFF-BI-10001597 | G64: 40.98 | H64: 5 | I64: 0.8 | J64: -65.568 | K64: =INDEX(product!B:B,MATCH('TABELA TOTAL'!$F7947,product!A:A,0)) -> Office Supplies | L64: =INDEX(product!C:C,MATCH(F64,product!A:A,)) -> Binders | M64: =INDEX(product!D:D,MATCH(F64,product!A:A,)) -> Wilson Jones Ledger-Size, Piano-Hinge Binder, 2", Blue
A65: CA-2017-134194 | B65: 43094 | C65: 43101 | D65: Standard Class | E65: GA-14725 | F65: OFF-BI-10001116 | G65: 3.168 | H65: 3 | I65: 0.8 | J65: -5.0688 | K65: =INDEX(product!B:B,MATCH('TABELA TOTAL'!$F7948,product!A:A,0)) -> Office Supplies | L65: =INDEX(product!C:C,MATCH(F65,product!A:A,)) -> Binders | M65: =INDEX(product!D:D,MATCH(F65,product!A:A,)) -> Wilson Jones 1" Hanging DublLock Ring Binders
A66: CA-2017-105620 | B66: 43094 | C66: 43097 | D66: First Class | E66: JH-15430 | F66: FUR-FU-10004963 | G66: 21 | H66: 3 | I66: 0.2 | J66: 5.775 | K66: =INDEX(product!B:B,MATCH('TABELA TOTAL'!$F8958,product!A:A,0)) -> Office Supplies | L66: =INDEX(product!C:C,MATCH(F66,product!A:A,)) -> Furnishings | M66: =INDEX(product!D:D,MATCH(F66,product!A:A,)) -> Eldon 400 Class Desk Accessories, Black Carbon
A67: CA-2017-105620 | B67: 43094 | C67: 43097 | D67: First Class | E67: JH-15430 | F67: TEC-MA-10004626 | G67: 120 | H67: 2 | I67: 0.5 | J67: -7.2 | K67: =INDEX(product!B:B,MATCH('TABELA TOTAL'!$F8959,product!A:A,0)) -> Office Supplies | L67: =INDEX(product!C:C,MATCH(F67,product!A:A,)) -> Machines | M67: =INDEX(product!D:D,MATCH(F67,product!A:A,)) -> Lexmark 20R1285 X6650 Wireless All-in-One Printer
A68: CA-2017-108756 | B68: 43094 | C68: 43098 | D68: Standard Class | E68: PO-18865 | F68: TEC-AC-10003237 | G68: 31.8 | H68: 3 | I68: 0 | J68: 13.674 | K68: =INDEX(product!B:B,MATCH('TABELA TOTAL'!$F9378,product!A:A,0)) -> Office Supplies | L68: =INDEX(product!C:C,MATCH(F68,product!A:A,)) -> Accessories | M68: =INDEX(product!D:D,MATCH(F68,product!A:A,)) -> Memorex Micro Travel Drive 4 GB
A69: CA-2017-117933 | B69: 43093 | C69: 43098 | D69: Standard Class | E69: RF-19840 | F69: OFF-AP-10004249 | G69: 35.91 | H69: 3 | I69: 0 | J69: 9.6957 | K69: =INDEX(product!B:B,MATCH('TABELA TOTAL'!$F406,product!A:A,0)) -> Office Supplies | L69: =INDEX(product!C:C,MATCH(F69,product!A:A,)) -> Appliances | M69: =INDEX(product!D:D,MATCH(F69,product!A:A,)) -> Staple holder
A70: CA-2017-154935 | B70: 43093 | C70: 43098 | D70: Standard Class | E70: AR-10540 | F70: OFF-BI-10003708 | G70: 17.88 | H70: 3 | I70: 0.2 | J70: 5.5875 | K70: =INDEX(product!B:B,MATCH('TABELA TOTAL'!$F1508,product!A:A,0)) -> Furniture | L70: =INDEX(product!C:C,MATCH(F70,product!A:A,)) -> Binders | M70: =INDEX(product!D:D,MATCH(F70,product!A:A,)) -> Acco Four Pocket Poly Ring Binder with Label Holder, Smoke, 1"
A71: CA-2017-147956 | B71: 43093 | C71: 43100 | D71: Standard Class | E71: AH-10210 | F71: OFF-ST-10001097 | G71: 1003.62 | H71: 6 | I71: 0 | J71: 0 | K71: =INDEX(product!B:B,MATCH('TABELA TOTAL'!$F2483,product!A:A,0)) -> Technology | L71: =INDEX(product!C:C,MATCH(F71,product!A:A,)) -> Storage | M71: =INDEX(product!D:D,MATCH(F71,product!A:A,)) -> Office Impressions Heavy Duty Welded Shelving & Multimedia Storage Drawers
A72: CA-2017-169978 | B72: 43093 | C72: 43097 | D72: Standard Class | E72: HG-15025 | F72: FUR-CH-10002602 | G72: 271.764 | H72: 2 | I72: 0.1 | J72: 48.3136 | K72: =INDEX(product!B:B,MATCH('TABELA TOTAL'!$F3316,product!A:A,0)) -> Technology | L72: =INDEX(product!C:C,MATCH(F72,product!A:A,)) -> Chairs | M72: =INDEX(product!D:D,MATCH(F72,product!A:A,)) -> DMI Arturo Collection Mission-style Design Wood Chair
A73: CA-2017-169978 | B73: 43093 | C73: 43097 | D73: Standard Class | E73: HG-15025 | F73: OFF-BI-10001900 | G73: 14.376 | H73: 3 | I73: 0.2 | J73: 4.8519 | K73: =INDEX(product!B:B,MATCH('TABELA TOTAL'!$F3317,product!A:A,0)) -> Office Supplies | L73: =INDEX(product!C:C,MATCH(F73,product!A:A,)) -> Binders | M73: =INDEX(product!D:D,MATCH(F73,product!A:A,)) -> DXL Angle-View Binders with Locking Rings, Black
A74: CA-2017-169411 | B74: 43093 | C74: 43098 | D74: Standard Class | E74: AC-10615 | F74: FUR-FU-10001602 | G74: 37.93 | H74: 1 | I74: 0 | J74: 6.8274 | K74: =INDEX(product!B:B,MATCH('TABELA TOTAL'!$F3702,product!A:A,0)) -> Office Supplies | L74: =INDEX(product!C:C,MATCH(F74,product!A:A,)) -> Furnishings | M74: =INDEX(product!D:D,MATCH(F74,product!A:A,)) -> Eldon Delta Triangular Chair Mat, 52" x 58", Clear
A75: CA-2017-124296 | B75: 43093 | C75: 43097 | D75: Standard Class | E75: CS-12355 | F75: TEC-MA-10003183 | G75: 479.97 | H75: 3 | I75: 0 | J75: 239.985 | K75: =INDEX(product!B:B,MATCH('TABELA TOTAL'!$F4031,product!A:A,0)) -> Furniture | L75: =INDEX(product!C:C,MATCH(F75,product!A:A,)) -> Machines | M75: =INDEX(product!D:D,MATCH(F75,product!A:A,)) -> DYMO CardScan Personal V9 Business Card Scanner
A76: CA-2017-124296 | B76: 43093 | C76: 43097 | D76: Standard Class | E76: CS-12355 | F76: FUR-CH-10002439 | G76: 232.88 | H76: 4 | I76: 0 | J76: 60.5488 | K76: =INDEX(product!B:B,MATCH('TABELA TOTAL'!$F4032,product!A:A,0)) -> Technology | L76: =INDEX(product!C:C,MATCH(F76,product!A:A,)) -> Chairs | M76: =INDEX(product!D:D,MATCH(F76,product!A:A,)) -> Iceberg Nesting Folding Chair, 19w x 6d x 43h
A77: CA-2017-145219 | B77: 43093 | C77: 43094 | D77: First Class | E77: RM-19675 | F77: TEC-CO-10001449 | G77: 2879.952 | H77: 6 | I77: 0.2 | J77: 1007.9832 | K77: =INDEX(product!B:B,MATCH('TABELA TOTAL'!$F4621,product!A:A,0)) -> Office Supplies | L77: =INDEX(product!C:C,MATCH(F77,product!A:A,)) -> Copiers | M77: =INDEX(product!D:D,MATCH(F77,product!A:A,)) -> Hewlett Packard LaserJet 3310 Copier
A78: CA-2017-145219 | B78: 43093 | C78: 43094 | D78: First Class | E78: RM-19675 | F78: OFF-BI-10001670 | G78: 90.48 | H78: 3 | I78: 0.2 | J78: 33.93 | K78: =INDEX(product!B:B,MATCH('TABELA TOTAL'!$F4622,product!A:A,0)) -> Office Supplies | L78: =INDEX(product!C:C,MATCH(F78,product!A:A,)) -> Binders | M78: =INDEX(product!D:D,MATCH(F78,product!A:A,)) -> Vinyl Sectional Post Binders
A79: CA-2017-128734 | B79: 43093 | C79: 43100 | D79: Standard Class | E79: JL-15175 | F79: FUR-FU-10001731 | G79: 8.544 | H79: 4 | I79: 0.2 | J79: 1.9224 | K79: =INDEX(product!B:B,MATCH('TABELA TOTAL'!$F5149,product!A:A,0)) -> Office Supplies | L79: =INDEX(product!C:C,MATCH(F79,product!A:A,)) -> Furnishings | M79: =INDEX(product!D:D,MATCH(F79,product!A:A,)) -> Acrylic Self-Standing Desk Frames
A80: CA-2017-128734 | B80: 43093 | C80: 43100 | D80: Standard Class | E80: JL-15175 | F80: FUR-CH-10001394 | G80: 842.376 | H80: 3 | I80: 0.2 | J80: 105.297 | K80: =INDEX(product!B:B,MATCH('TABELA TOTAL'!$F5150,product!A:A,0)) -> Office Supplies | L80: =INDEX(product!C:C,MATCH(F80,product!A:A,)) -> Chairs | M80: =INDEX(product!D:D,MATCH(F80,product!A:A,)) -> Global Leather Executive Chair
A81: CA-2017-121195 | B81: 43093 | C81: 43096 | D81: First Class | E81: NS-18505 | F81: OFF-ST-10000585 | G81: 264.32 | H81: 2 | I81: 0.2 | J81: 19.824 | K81: =INDEX(product!B:B,MATCH('TABELA TOTAL'!$F7609,product!A:A,0)) -> Technology | L81: =INDEX(product!C:C,MATCH(F81,product!A:A,)) -> Storage | M81: =INDEX(product!D:D,MATCH(F81,product!A:A,)) -> Economy Rollaway Files
A82: CA-2017-163671 | B82: 43093 | C82: 43099 | D82: Standard Class | E82: DP-13105 | F82: OFF-BI-10001679 | G82: 21.312 | H82: 3 | I82: 0.2 | J82: 7.992 | K82: =INDEX(product!B:B,MATCH('TABELA TOTAL'!$F8857,product!A:A,0)) -> Technology | L82: =INDEX(product!C:C,MATCH(F82,product!A:A,)) -> Binders | M82: =INDEX(product!D:D,MATCH(F82,product!A:A,)) -> GBC Instant Index System for Binding Systems
A83: CA-2017-148355 | B83: 43093 | C83: 43097 | D83: Standard Class | E83: NC-18535 | F83: OFF-PA-10001972 | G83: 19.44 | H83: 3 | I83: 0 | J83: 9.3312 | K83: =INDEX(product!B:B,MATCH('TABELA TOTAL'!$F8948,product!A:A,0)) -> Furniture | L83: =INDEX(product!C:C,MATCH(F83,product!A:A,)) -> Paper | M83: =INDEX(product!D:D,MATCH(F83,product!A:A,)) -> Xerox 214
A84: CA-2017-148355 | B84: 43093 | C84: 43097 | D84: Standard Class | E84: NC-18535 | F84: OFF-BI-10000201 | G84: 12.3 | H84: 5 | I84: 0 | J84: 6.15 | K84: =INDEX(product!B:B,MATCH('TABELA TOTAL'!$F8949,product!A:A,0)) -> Technology | L84: =INDEX(product!C:C,MATCH(F84,product!A:A,)) -> Binders | M84: =INDEX(product!D:D,MATCH(F84,product!A:A,)) -> Avery Triangle Shaped Sheet Lifters, Black, 2/Pack
A85: US-2017-123463 | B85: 43092 | C85: 43092 | D85: Same Day | E85: GZ-14470 | F85: OFF-AR-10001118 | G85: 13.48 | H85: 4 | I85: 0 | J85: 5.9312 | K85: =INDEX(product!B:B,MATCH('TABELA TOTAL'!$F884,product!A:A,0)) -> Technology | L85: =INDEX(product!C:C,MATCH(F85,product!A:A,)) -> Art | M85: =INDEX(product!D:D,MATCH(F85,product!A:A,)) -> Binney & Smith Crayola Metallic Crayons, 16-Color Pack
A86: CA-2017-127929 | B86: 43092 | C86: 43096 | D86: Standard Class | E86: FM-14215 | F86: FUR-FU-10003708 | G86: 181.95 | H86: 3 | I86: 0 | J86: 38.2095 | K86: =INDEX(product!B:B,MATCH('TABELA TOTAL'!$F2296,product!A:A,0)) -> Technology | L86: =INDEX(product!C:C,MATCH(F86,product!A:A,)) -> Furnishings | M86: =INDEX(product!D:D,MATCH(F86,product!A:A,)) -> Tenex Traditional Chairmats for Medium Pile Carpet, Standard Lip, 36" x 48"
A87: CA-2017-121216 | B87: 43092 | C87: 43094 | D87: Second Class | E87: MM-17920 | F87: OFF-PA-10004519 | G87: 28.672 | H87: 8 | I87: 0.2 | J87: 10.3936 | K87: =INDEX(product!B:B,MATCH('TABELA TOTAL'!$F3546,product!A:A,0)) -> Technology | L87: =INDEX(product!C:C,MATCH(F87,product!A:A,)) -> Paper | M87: =INDEX(product!D:D,MATCH(F87,product!A:A,)) -> Spiral Phone Message Books with Labels by Adams
A88: CA-2017-121216 | B88: 43092 | C88: 43094 | D88: Second Class | E88: MM-17920 | F88: OFF-AP-10001947 | G88: 29.312 | H88: 8 | I88: 0.8 | J88: -74.7456 | K88: =INDEX(product!B:B,MATCH('TABELA TOTAL'!$F3547,product!A:A,0)) -> Office Supplies | L88: =INDEX(product!C:C,MATCH(F88,product!A:A,)) -> Appliances | M88: =INDEX(product!D:D,MATCH(F88,product!A:A,)) -> Acco 6 Outlet Guardian Premium Plus Surge Suppressor
A89: CA-2017-140627 | B89: 43092 | C89: 43096 | D89: Standard Class | E89: DK-12985 | F89: FUR-FU-10000087 | G89: 72.704 | H89: 4 | I89: 0.2 | J89: 19.0848 | K89: =INDEX(product!B:B,MATCH('TABELA TOTAL'!$F6224,product!A:A,0)) -> Office Supplies | L89: =INDEX(product!C:C,MATCH(F89,product!A:A,)) -> Furnishings | M89: =INDEX(product!D:D,MATCH(F89,product!A:A,)) -> Executive Impressions 14" Two-Color Numerals Wall Clock
A90: CA-2017-140627 | B90: 43092 | C90: 43096 | D90: Standard Class | E90: DK-12985 | F90: OFF-AR-10000422 | G90: 12.264 | H90: 7 | I90: 0.2 | J90: 1.0731 | K90: =INDEX(product!B:B,MATCH('TABELA TOTAL'!$F6225,product!A:A,0)) -> Furniture | L90: =INDEX(product!C:C,MATCH(F90,product!A:A,)) -> Art | M90: =INDEX(product!D:D,MATCH(F90,product!A:A,)) -> Pencil and Crayon Sharpener
A91: CA-2017-140627 | B91: 43092 | C91: 43096 | D91: Standard Class | E91: DK-12985 | F91: OFF-ST-10004123 | G91: 218.352 | H91: 3 | I91: 0.2 | J91: -54.588 | K91: =INDEX(product!B:B,MATCH('TABELA TOTAL'!$F6226,product!A:A,0)) -> Furniture | L91: =INDEX(product!C:C,MATCH(F91,product!A:A,)) -> Storage | M91: =INDEX(product!D:D,MATCH(F91,product!A:A,)) -> Safco Industrial Wire Shelving System
A92: US-2017-162670 | B92: 43092 | C92: 43097 | D92: Second Class | E92: MF-18250 | F92: OFF-ST-10001328 | G92: 62.04 | H92: 4 | I92: 0 | J92: 17.3712 | K92: =INDEX(product!B:B,MATCH('TABELA TOTAL'!$F6854,product!A:A,0)) -> Furniture | L92: =INDEX(product!C:C,MATCH(F92,product!A:A,)) -> Storage | M92: =INDEX(product!D:D,MATCH(F92,product!A:A,)) -> Personal Filing Tote with Lid, Black/Gray
A93: US-2017-162670 | B93: 43092 | C93: 43097 | D93: Second Class | E93: MF-18250 | F93: TEC-PH-10003601 | G93: 494.97 | H93: 3 | I93: 0 | J93: 148.491 | K93: =INDEX(product!B:B,MATCH('TABELA TOTAL'!$F6855,product!A:A,0)) -> Office Supplies | L93: =INDEX(product!C:C,MATCH(F93,product!A:A,)) -> Phones | M93: =INDEX(product!D:D,MATCH(F93,product!A:A,)) -> Ativa D5772 2-Line 5.8GHz Digital Expandable Corded/Cordless Phone System with Answering & Caller ID/Call Waiting, Black/Silver
A94: US-2017-162670 | B94: 43092 | C94: 43097 | D94: Second Class | E94: MF-18250 | F94: OFF-ST-10001522 | G94: 367.96 | H94: 4 | I94: 0 | J94: 14.7184 | K94: =INDEX(product!B:B,MATCH('TABELA TOTAL'!$F6856,product!A:A,0)) -> Furniture | L94: =INDEX(product!C:C,MATCH(F94,product!A:A,)) -> Storage | M94: =INDEX(product!D:D,MATCH(F94,product!A:A,)) -> Gould Plastics 18-Pocket Panel Bin, 34w x 5-1/4d x 20-1/2h
A95: US-2017-162670 | B95: 43092 | C95: 43097 | D95: Second Class | E95: MF-18250 | F95: OFF-PA-10001994 | G95: 44.96 | H95: 2 | I95: 0 | J95: 20.6816 | K95: =INDEX(product!B:B,MATCH('TABELA TOTAL'!$F6857,product!A:A,0)) -> Technology | L95: =INDEX(product!C:C,MATCH(F95,product!A:A,)) -> Paper | M95: =INDEX(product!D:D,MATCH(F95,product!A:A,)) -> Ink Jet Note and Greeting Cards, 8-1/2" x 5-1/2" Card Size
A96: US-2017-162670 | B96: 43092 | C96: 43097 | D96: Second Class | E96: MF-18250 | F96: OFF-EN-10001453 | G96: 182.94 | H96: 3 | I96: 0 | J96: 85.9818 | K96: =INDEX(product!B:B,MATCH('TABELA TOTAL'!$F6858,product!A:A,0)) -> Office Supplies | L96: =INDEX(product!C:C,MATCH(F96,product!A:A,)) -> Envelopes | M96: =INDEX(product!D:D,MATCH(F96,product!A:A,)) -> Tyvek Interoffice Envelopes, 9 1/2" x 12 1/2", 100/Box
A97: CA-2017-117443 | B97: 43092 | C97: 43094 | D97: Second Class | E97: JB-15400 | F97: OFF-BI-10004002 | G97: 13.84 | H97: 4 | I97: 0.8 | J97: -22.144 | K97: =INDEX(product!B:B,MATCH('TABELA TOTAL'!$F6998,product!A:A,0)) -> Furniture | L97: =INDEX(product!C:C,MATCH(F97,product!A:A,)) -> Binders | M97: =INDEX(product!D:D,MATCH(F97,product!A:A,)) -> Wilson Jones International Size A4 Ring Binders
A98: CA-2017-117443 | B98: 43092 | C98: 43094 | D98: Second Class | E98: JB-15400 | F98: OFF-PA-10004475 | G98: 175.872 | H98: 4 | I98: 0.2 | J98: 63.7536 | K98: =INDEX(product!B:B,MATCH('TABELA TOTAL'!$F6999,product!A:A,0)) -> Office Supplies | L98: =INDEX(product!C:C,MATCH(F98,product!A:A,)) -> Paper | M98: =INDEX(product!D:D,MATCH(F98,product!A:A,)) -> Xerox 1940
A99: CA-2017-110625 | B99: 43092 | C99: 43099 | D99: Standard Class | E99: JB-16045 | F99: FUR-FU-10001473 | G99: 27.46 | H99: 2 | I99: 0 | J99: 9.8856 | K99: =INDEX(product!B:B,MATCH('TABELA TOTAL'!$F8393,product!A:A,0)) -> Office Supplies | L99: =INDEX(product!C:C,MATCH(F99,product!A:A,)) -> Furnishings | M99: =INDEX(product!D:D,MATCH(F99,product!A:A,)) -> DAX Wood Document Frame
A100: CA-2017-155376 | B100: 43091 | C100: 43096 | D100: Standard Class | E100: SG-20080 | F100: OFF-AP-10001058 | G100: 839.43 | H100: 3 | I100: 0 | J100: 218.2518 | K100: =INDEX(product!B:B,MATCH('TABELA TOTAL'!$F146,product!A:A,0)) -> Office Supplies | L100: =INDEX(product!C:C,MATCH(F100,product!A:A,)) -> Appliances | M100: =INDEX(product!D:D,MATCH(F100,product!A:A,)) -> Sanyo 2.5 Cubic Foot Mid-Size Office Refrigerators
...

Sheet RFM
A1: {=_xlfn.UNIQUE('TABELA TOTAL'!E:E)} -> Customer ID | B1: Recencia | C1: Frequencia | D1: Monetizaçao | E1: Nota R | F1: Nota F | G1: Nota M | H1: Média MF | I1: Nome do Segmento | K1: Recencia | L1: Frequencia & Monetizaçao | M1: Segmento | N1: Nome do Segmento
A2: CC-12430 | B2: {=MAX('TABELA TOTAL'!B:B) - MAX(IF('TABELA TOTAL'!E:E =RFM!A2,'TABELA TOTAL'!B:B))} -> 0 | C2: {=COUNTA(_xlfn.UNIQUE(_xlfn._xlws.FILTER('TABELA TOTAL'!A:A,'TABELA TOTAL'!E:E=RFM!A2)))} -> 10 | D2: =SUMIF('TABELA TOTAL'!E:E,RFM!A2,'TABELA TOTAL'!G:G) -> 2870.05 | E2: {=_xlfn.IFS(B2:B795<=72,5,B2:B7945<=145,4,B2:B795<=218,3,B2:B795<=292,2,B2:B2795<=365,1)} -> 5 | F2: {=_xlfn.IFS(C2:C795<=3,1,C2:C795<=6,2,C2:C795<=9,3,C2:C795<=12,4,C2:C795<=15,5)} -> 4 | G2: {=_xlfn.IFS(D2<=_xlfn.PERCENTILE.INC(D:D,0.2),1, D2<=_xlfn.PERCENTILE.INC(D:D,0.4),2, D2<=_xlfn.PERCENTILE.INC(D:D,0.6),3, D3<=_xlfn.PERCENTILE.INC(D:D,0.8),4, TRUE,5)} -> 4 | H2: =ROUND(AVERAGE(F2,G2),0) -> 4 | I2: {=INDEX($N$2:$N$26,MATCH(1,($K$2:$K$26=$E2)*($L$2:$L$26=$H2),0))} -> Fiéis | K2: 1 | L2: 1 | M2: K | N2: Perdidos | S2: Row Labels | T2: Count of Customer ID | V2: Segmento | W2: Grupo | X2: Clientes
A3: PO-18865 | B3: {=MAX('TABELA TOTAL'!B:B) - MAX(IF('TABELA TOTAL'!E:E =RFM!A3,'TABELA TOTAL'!B:B))} -> 0 | C3: {=COUNTA(_xlfn.UNIQUE(_xlfn._xlws.FILTER('TABELA TOTAL'!A:A,'TABELA TOTAL'!E:E=RFM!A3)))} -> 7 | D3: =SUMIF('TABELA TOTAL'!E:E,RFM!A3,'TABELA TOTAL'!G:G) -> 2493.214 | E3: 5 | F3: 3 | G3: {=_xlfn.IFS(D3<=_xlfn.PERCENTILE.INC(D:D,0.2),1, D3<=_xlfn.PERCENTILE.INC(D:D,0.4),2, D3<=_xlfn.PERCENTILE.INC(D:D,0.6),3, D4<=_xlfn.PERCENTILE.INC(D:D,0.8),4, TRUE,5)} -> 3 | H3: =ROUND(AVERAGE(F3,G3),0) -> 3 | I3: {=INDEX($N$2:$N$26,MATCH(1,($K$2:$K$26=$E3)*($L$2:$L$26=$H3),0))} -> Fiéis Potencial | K3: 1 | L3: 2 | M3: K | N3: Perdidos | S3: Campeão | T3: 0.028860029 | V3: Campeão | W3: Campeão | X3: 0.028860029
A4: EB-13975 | B4: {=MAX('TABELA TOTAL'!B:B) - MAX(IF('TABELA TOTAL'!E:E =RFM!A4,'TABELA TOTAL'!B:B))} -> 0 | C4: {=COUNTA(_xlfn.UNIQUE(_xlfn._xlws.FILTER('TABELA TOTAL'!A:A,'TABELA TOTAL'!E:E=RFM!A4)))} -> 4 | D4: =SUMIF('TABELA TOTAL'!E:E,RFM!A4,'TABELA TOTAL'!G:G) -> 1643.255 | E4: 5 | F4: 2 | G4: {=_xlfn.IFS(D4<=_xlfn.PERCENTILE.INC(D:D,0.2),1, D4<=_xlfn.PERCENTILE.INC(D:D,0.4),2, D4<=_xlfn.PERCENTILE.INC(D:D,0.6),3, D5<=_xlfn.PERCENTILE.INC(D:D,0.8),4, TRUE,5)} -> 2 | H4: =ROUND(AVERAGE(F4,G4),0) -> 2 | I4: {=INDEX($N$2:$N$26,MATCH(1,($K$2:$K$26=$E4)*($L$2:$L$26=$H4),0))} -> Fiéis Potencial | K4: 1 | L4: 3 | M4: I | N4: Risco | S4: Fiéis | T4: 0.31313131 | V4: Fiéis | W4: Fiéis | X4: 0.31313131
A5: JM-15580 | B5: {=MAX('TABELA TOTAL'!B:B) - MAX(IF('TABELA TOTAL'!E:E =RFM!A5,'TABELA TOTAL'!B:B))} -> 0 | C5: {=COUNTA(_xlfn.UNIQUE(_xlfn._xlws.FILTER('TABELA TOTAL'!A:A,'TABELA TOTAL'!E:E=RFM!A5)))} -> 5 | D5: =SUMIF('TABELA TOTAL'!E:E,RFM!A5,'TABELA TOTAL'!G:G) -> 303.948 | E5: 5 | F5: 2 | G5: {=_xlfn.IFS(D5<=_xlfn.PERCENTILE.INC(D:D,0.2),1, D5<=_xlfn.PERCENTILE.INC(D:D,0.4),2, D5<=_xlfn.PERCENTILE.INC(D:D,0.6),3, D6<=_xlfn.PERCENTILE.INC(D:D,0.8),4, TRUE,5)} -> 1 | H5: =ROUND(AVERAGE(F5,G5),0) -> 2 | I5: {=INDEX($N$2:$N$26,MATCH(1,($K$2:$K$26=$E5)*($L$2:$L$26=$H5),0))} -> Fiéis Potencial | K5: 1 | L5: 4 | M5: I | N5: Risco | S5: Fiéis Potencial | T5: 0.46753247 | V5: Fiéis Potencial | W5: Fiéis Potencial | X5: 0.46753247
A6: JG-15160 | B6: {=MAX('TABELA TOTAL'!B:B) - MAX(IF('TABELA TOTAL'!E:E =RFM!A6,'TABELA TOTAL'!B:B))} -> 1 | C6: {=COUNTA(_xlfn.UNIQUE(_xlfn._xlws.FILTER('TABELA TOTAL'!A:A,'TABELA TOTAL'!E:E=RFM!A6)))} -> 11 | D6: =SUMIF('TABELA TOTAL'!E:E,RFM!A6,'TABELA TOTAL'!G:G) -> 6366.392 | E6: 5 | F6: 4 | G6: {=_xlfn.IFS(D6<=_xlfn.PERCENTILE.INC(D:D,0.2),1, D6<=_xlfn.PERCENTILE.INC(D:D,0.4),2, D6<=_xlfn.PERCENTILE.INC(D:D,0.6),3, D7<=_xlfn.PERCENTILE.INC(D:D,0.8),4, TRUE,5)} -> 4 | H6: =ROUND(AVERAGE(F6,G6),0) -> 4 | I6: {=INDEX($N$2:$N$26,MATCH(1,($K$2:$K$26=$E6)*($L$2:$L$26=$H6),0))} -> Fiéis | K6: 1 | L6: 5 | M6: H | N6: Não Perder | S6: Hibernando | T6: 0.02020202 | V6: Hibernando | W6: Hibernando | X6: 0.02020202
A7: MC-17845 | B7: {=MAX('TABELA TOTAL'!B:B) - MAX(IF('TABELA TOTAL'!E:E =RFM!A7,'TABELA TOTAL'!B:B))} -> 1 | C7: {=COUNTA(_xlfn.UNIQUE(_xlfn._xlws.FILTER('TABELA TOTAL'!A:A,'TABELA TOTAL'!E:E=RFM!A7)))} -> 7 | D7: =SUMIF('TABELA TOTAL'!E:E,RFM!A7,'TABELA TOTAL'!G:G) -> 3805.714 | E7: 5 | F7: 3 | G7: {=_xlfn.IFS(D7<=_xlfn.PERCENTILE.INC(D:D,0.2),1, D7<=_xlfn.PERCENTILE.INC(D:D,0.4),2, D7<=_xlfn.PERCENTILE.INC(D:D,0.6),3, D8<=_xlfn.PERCENTILE.INC(D:D,0.8),4, TRUE,5)} -> 4 | H7: =ROUND(AVERAGE(F7,G7),0) -> 4 | I7: {=INDEX($N$2:$N$26,MATCH(1,($K$2:$K$26=$E7)*($L$2:$L$26=$H7),0))} -> Fiéis | K7: 2 | L7: 1 | M7: K | N7: Perdidos | S7: Não Perder | T7: 0.0014430014 | V7: Não Perder | W7: Não Perder | X7: 0.0014430014
A8: KB-16600 | B8: {=MAX('TABELA TOTAL'!B:B) - MAX(IF('TABELA TOTAL'!E:E =RFM!A8,'TABELA TOTAL'!B:B))} -> 1 | C8: {=COUNTA(_xlfn.UNIQUE(_xlfn._xlws.FILTER('TABELA TOTAL'!A:A,'TABELA TOTAL'!E:E=RFM!A8)))} -> 7 | D8: =SUMIF('TABELA TOTAL'!E:E,RFM!A8,'TABELA TOTAL'!G:G) -> 983.922 | E8: 5 | F8: 3 | G8: {=_xlfn.IFS(D8<=_xlfn.PERCENTILE.INC(D:D,0.2),1, D8<=_xlfn.PERCENTILE.INC(D:D,0.4),2, D8<=_xlfn.PERCENTILE.INC(D:D,0.6),3, D9<=_xlfn.PERCENTILE.INC(D:D,0.8),4, TRUE,5)} -> 2 | H8: =ROUND(AVERAGE(F8,G8),0) -> 3 | I8: {=INDEX($N$2:$N$26,MATCH(1,($K$2:$K$26=$E8)*($L$2:$L$26=$H8),0))} -> Fiéis Potencial | K8: 2 | L8: 2 | M8: J | N8: Hibernando | S8: Novos Clientes | T8: 0.025974026 | V8: Novos Clientes | W8: Novos Clientes | X8: 0.025974026
A9: BP-11185 | B9: {=MAX('TABELA TOTAL'!B:B) - MAX(IF('TABELA TOTAL'!E:E =RFM!A9,'TABELA TOTAL'!B:B))} -> 1 | C9: {=COUNTA(_xlfn.UNIQUE(_xlfn._xlws.FILTER('TABELA TOTAL'!A:A,'TABELA TOTAL'!E:E=RFM!A9)))} -> 9 | D9: =SUMIF('TABELA TOTAL'!E:E,RFM!A9,'TABELA TOTAL'!G:G) -> 3675.861 | E9: 5 | F9: 3 | G9: {=_xlfn.IFS(D9<=_xlfn.PERCENTILE.INC(D:D,0.2),1, D9<=_xlfn.PERCENTILE.INC(D:D,0.4),2, D9<=_xlfn.PERCENTILE.INC(D:D,0.6),3, D10<=_xlfn.PERCENTILE.INC(D:D,0.8),4, TRUE,5)} -> 4 | H9: =ROUND(AVERAGE(F9,G9),0) -> 4 | I9: {=INDEX($N$2:$N$26,MATCH(1,($K$2:$K$26=$E9)*($L$2:$L$26=$H9),0))} -> Fiéis | K9: 2 | L9: 3 | M9: I | N9: Risco | S9: Perdidos | T9: 0.027417027 | V9: Perdidos | W9: Perdidos | X9: 0.027417027
A10: BS-11755 | B10: {=MAX('TABELA TOTAL'!B:B) - MAX(IF('TABELA TOTAL'!E:E =RFM!A10,'TABELA TOTAL'!B:B))} -> 1 | C10: {=COUNTA(_xlfn.UNIQUE(_xlfn._xlws.FILTER('TABELA TOTAL'!A:A,'TABELA TOTAL'!E:E=RFM!A10)))} -> 7 | D10: =SUMIF('TABELA TOTAL'!E:E,RFM!A10,'TABELA TOTAL'!G:G) -> 2562.382 | E10: 5 | F10: 3 | G10: {=_xlfn.IFS(D10<=_xlfn.PERCENTILE.INC(D:D,0.2),1, D10<=_xlfn.PERCENTILE.INC(D:D,0.4),2, D10<=_xlfn.PERCENTILE.INC(D:D,0.6),3, D11<=_xlfn.PERCENTILE.INC(D:D,0.8),4, TRUE,5)} -> 3 | H10: =ROUND(AVERAGE(F10,G10),0) -> 3 | I10: {=INDEX($N$2:$N$26,MATCH(1,($K$2:$K$26=$E10)*($L$2:$L$26=$H10),0))} -> Fiéis Potencial | K10: 2 | L10: 4 | M10: I | N10: Risco | S10: Precisam Atenção | T10: 0.023088023 | V10: Precisam Atenção | W10: Precisam Atenção | X10: 0.023088023
A11: KH-16360 | B11: {=MAX('TABELA TOTAL'!B:B) - MAX(IF('TABELA TOTAL'!E:E =RFM!A11,'TABELA TOTAL'!B:B))} -> 1 | C11: {=COUNTA(_xlfn.UNIQUE(_xlfn._xlws.FILTER('TABELA TOTAL'!A:A,'TABELA TOTAL'!E:E=RFM!A11)))} -> 6 | D11: =SUMIF('TABELA TOTAL'!E:E,RFM!A11,'TABELA TOTAL'!G:G) -> 3100.612 | E11: 5 | F11: 2 | G11: {=_xlfn.IFS(D11<=_xlfn.PERCENTILE.INC(D:D,0.2),1, D11<=_xlfn.PERCENTILE.INC(D:D,0.4),2, D11<=_xlfn.PERCENTILE.INC(D:D,0.6),3, D12<=_xlfn.PERCENTILE.INC(D:D,0.8),4, TRUE,5)} -> 5 | H11: =ROUND(AVERAGE(F11,G11),0) -> 4 | I11: {=INDEX($N$2:$N$26,MATCH(1,($K$2:$K$26=$E11)*($L$2:$L$26=$H11),0))} -> Fiéis | K11: 2 | L11: 5 | M11: H | N11: Não Perder | S11: Promissores | T11: 0.01010101 | V11: Promissores | W11: Promissores | X11: 0.01010101
A12: KH-16690 | B12: {=MAX('TABELA TOTAL'!B:B) - MAX(IF('TABELA TOTAL'!E:E =RFM!A12,'TABELA TOTAL'!B:B))} -> 2 | C12: {=COUNTA(_xlfn.UNIQUE(_xlfn._xlws.FILTER('TABELA TOTAL'!A:A,'TABELA TOTAL'!E:E=RFM!A12)))} -> 7 | D12: =SUMIF('TABELA TOTAL'!E:E,RFM!A12,'TABELA TOTAL'!G:G) -> 5990.799 | E12: 5 | F12: 3 | G12: {=_xlfn.IFS(D12<=_xlfn.PERCENTILE.INC(D:D,0.2),1, D12<=_xlfn.PERCENTILE.INC(D:D,0.4),2, D12<=_xlfn.PERCENTILE.INC(D:D,0.6),3, D13<=_xlfn.PERCENTILE.INC(D:D,0.8),4, TRUE,5)} -> 4 | H12: =ROUND(AVERAGE(F12,G12),0) -> 4 | I12: {=INDEX($N$2:$N$26,MATCH(1,($K$2:$K$26=$E12)*($L$2:$L$26=$H12),0))} -> Fiéis | K12: 3 | L12: 1 | M12: G | N12: Quase Dormentes | S12: Quase Dormentes | T12: 0.04040404 | V12: Quase Dormentes | W12: Quase Dormentes | X12: 0.04040404
A13: JF-15415 | B13: {=MAX('TABELA TOTAL'!B:B) - MAX(IF('TABELA TOTAL'!E:E =RFM!A13,'TABELA TOTAL'!B:B))} -> 2 | C13: {=COUNTA(_xlfn.UNIQUE(_xlfn._xlws.FILTER('TABELA TOTAL'!A:A,'TABELA TOTAL'!E:E=RFM!A13)))} -> 6 | D13: =SUMIF('TABELA TOTAL'!E:E,RFM!A13,'TABELA TOTAL'!G:G) -> 2371.448 | E13: 5 | F13: 2 | G13: {=_xlfn.IFS(D13<=_xlfn.PERCENTILE.INC(D:D,0.2),1, D13<=_xlfn.PERCENTILE.INC(D:D,0.4),2, D13<=_xlfn.PERCENTILE.INC(D:D,0.6),3, D14<=_xlfn.PERCENTILE.INC(D:D,0.8),4, TRUE,5)} -> 3 | H13: =ROUND(AVERAGE(F13,G13),0) -> 3 | I13: {=INDEX($N$2:$N$26,MATCH(1,($K$2:$K$26=$E13)*($L$2:$L$26=$H13),0))} -> Fiéis Potencial | K13: 3 | L13: 2 | M13: G | N13: Quase Dormentes | S13: Risco | T13: 0.041847042 | V13: Risco | W13: Risco | X13: 0.041847042
A14: GH-14665 | B14: {=MAX('TABELA TOTAL'!B:B) - MAX(IF('TABELA TOTAL'!E:E =RFM!A14,'TABELA TOTAL'!B:B))} -> 2 | C14: {=COUNTA(_xlfn.UNIQUE(_xlfn._xlws.FILTER('TABELA TOTAL'!A:A,'TABELA TOTAL'!E:E=RFM!A14)))} -> 2 | D14: =SUMIF('TABELA TOTAL'!E:E,RFM!A14,'TABELA TOTAL'!G:G) -> 146.9408 | E14: 5 | F14: 1 | G14: {=_xlfn.IFS(D14<=_xlfn.PERCENTILE.INC(D:D,0.2),1, D14<=_xlfn.PERCENTILE.INC(D:D,0.4),2, D14<=_xlfn.PERCENTILE.INC(D:D,0.6),3, D15<=_xlfn.PERCENTILE.INC(D:D,0.8),4, TRUE,5)} -> 1 | H14: =ROUND(AVERAGE(F14,G14),0) -> 1 | I14: {=INDEX($N$2:$N$26,MATCH(1,($K$2:$K$26=$E14)*($L$2:$L$26=$H14),0))} -> Novos Clientes | K14: 3 | L14: 3 | M14: F | N14: Precisam Atenção
A15: HM-14860 | B15: {=MAX('TABELA TOTAL'!B:B) - MAX(IF('TABELA TOTAL'!E:E =RFM!A15,'TABELA TOTAL'!B:B))} -> 2 | C15: {=COUNTA(_xlfn.UNIQUE(_xlfn._xlws.FILTER('TABELA TOTAL'!A:A,'TABELA TOTAL'!E:E=RFM!A15)))} -> 10 | D15: =SUMIF('TABELA TOTAL'!E:E,RFM!A15,'TABELA TOTAL'!G:G) -> 8236.7648 | E15: 5 | F15: 4 | G15: {=_xlfn.IFS(D15<=_xlfn.PERCENTILE.INC(D:D,0.2),1, D15<=_xlfn.PERCENTILE.INC(D:D,0.4),2, D15<=_xlfn.PERCENTILE.INC(D:D,0.6),3, D16<=_xlfn.PERCENTILE.INC(D:D,0.8),4, TRUE,5)} -> 4 | H15: =ROUND(AVERAGE(F15,G15),0) -> 4 | I15: {=INDEX($N$2:$N$26,MATCH(1,($K$2:$K$26=$E15)*($L$2:$L$26=$H15),0))} -> Fiéis | K15: 3 | L15: 4 | M15: B | N15: Fiéis
A16: EH-14005 | B16: {=MAX('TABELA TOTAL'!B:B) - MAX(IF('TABELA TOTAL'!E:E =RFM!A16,'TABELA TOTAL'!B:B))} -> 2 | C16: {=COUNTA(_xlfn.UNIQUE(_xlfn._xlws.FILTER('TABELA TOTAL'!A:A,'TABELA TOTAL'!E:E=RFM!A16)))} -> 7 | D16: =SUMIF('TABELA TOTAL'!E:E,RFM!A16,'TABELA TOTAL'!G:G) -> 1219.53 | E16: 5 | F16: 3 | G16: {=_xlfn.IFS(D16<=_xlfn.PERCENTILE.INC(D:D,0.2),1, D16<=_xlfn.PERCENTILE.INC(D:D,0.4),2, D16<=_xlfn.PERCENTILE.INC(D:D,0.6),3, D17<=_xlfn.PERCENTILE.INC(D:D,0.8),4, TRUE,5)} -> 2 | H16: =ROUND(AVERAGE(F16,G16),0) -> 3 | I16: {=INDEX($N$2:$N$26,MATCH(1,($K$2:$K$26=$E16)*($L$2:$L$26=$H16),0))} -> Fiéis Potencial | K16: 3 | L16: 5 | M16: B | N16: Fiéis
A17: PC-18745 | B17: {=MAX('TABELA TOTAL'!B:B) - MAX(IF('TABELA TOTAL'!E:E =RFM!A17,'TABELA TOTAL'!B:B))} -> 2 | C17: {=COUNTA(_xlfn.UNIQUE(_xlfn._xlws.FILTER('TABELA TOTAL'!A:A,'TABELA TOTAL'!E:E=RFM!A17)))} -> 4 | D17: =SUMIF('TABELA TOTAL'!E:E,RFM!A17,'TABELA TOTAL'!G:G) -> 1832.064 | E17: 5 | F17: 2 | G17: {=_xlfn.IFS(D17<=_xlfn.PERCENTILE.INC(D:D,0.2),1, D17<=_xlfn.PERCENTILE.INC(D:D,0.4),2, D17<=_xlfn.PERCENTILE.INC(D:D,0.6),3, D18<=_xlfn.PERCENTILE.INC(D:D,0.8),4, TRUE,5)} -> 3 | H17: =ROUND(AVERAGE(F17,G17),0) -> 3 | I17: {=INDEX($N$2:$N$26,MATCH(1,($K$2:$K$26=$E17)*($L$2:$L$26=$H17),0))} -> Fiéis Potencial | K17: 4 | L17: 1 | M17: E | N17: Promissores
A18: JG-15310 | B18: {=MAX('TABELA TOTAL'!B:B) - MAX(IF('TABELA TOTAL'!E:E =RFM!A18,'TABELA TOTAL'!B:B))} -> 2 | C18: {=COUNTA(_xlfn.UNIQUE(_xlfn._xlws.FILTER('TABELA TOTAL'!A:A,'TABELA TOTAL'!E:E=RFM!A18)))} -> 6 | D18: =SUMIF('TABELA TOTAL'!E:E,RFM!A18,'TABELA TOTAL'!G:G) -> 2240.58 | E18: 5 | F18: 2 | G18: {=_xlfn.IFS(D18<=_xlfn.PERCENTILE.INC(D:D,0.2),1, D18<=_xlfn.PERCENTILE.INC(D:D,0.4),2, D18<=_xlfn.PERCENTILE.INC(D:D,0.6),3, D19<=_xlfn.PERCENTILE.INC(D:D,0.8),4, TRUE,5)} -> 3 | H18: =ROUND(AVERAGE(F18,G18),0) -> 3 | I18: {=INDEX($N$2:$N$26,MATCH(1,($K$2:$K$26=$E18)*($L$2:$L$26=$H18),0))} -> Fiéis Potencial | K18: 4 | L18: 2 | M18: C | N18: Fiéis Potencial
A19: LO-17170 | B19: {=MAX('TABELA TOTAL'!B:B) - MAX(IF('TABELA TOTAL'!E:E =RFM!A19,'TABELA TOTAL'!B:B))} -> 2 | C19: {=COUNTA(_xlfn.UNIQUE(_xlfn._xlws.FILTER('TABELA TOTAL'!A:A,'TABELA TOTAL'!E:E=RFM!A19)))} -> 5 | D19: =SUMIF('TABELA TOTAL'!E:E,RFM!A19,'TABELA TOTAL'!G:G) -> 644.35 | E19: 5 | F19: 2 | G19: {=_xlfn.IFS(D19<=_xlfn.PERCENTILE.INC(D:D,0.2),1, D19<=_xlfn.PERCENTILE.INC(D:D,0.4),2, D19<=_xlfn.PERCENTILE.INC(D:D,0.6),3, D20<=_xlfn.PERCENTILE.INC(D:D,0.8),4, TRUE,5)} -> 1 | H19: =ROUND(AVERAGE(F19,G19),0) -> 2 | I19: {=INDEX($N$2:$N$26,MATCH(1,($K$2:$K$26=$E19)*($L$2:$L$26=$H19),0))} -> Fiéis Potencial | K19: 4 | L19: 3 | M19: C | N19: Fiéis Potencial
A20: CS-12400 | B20: {=MAX('TABELA TOTAL'!B:B) - MAX(IF('TABELA TOTAL'!E:E =RFM!A20,'TABELA TOTAL'!B:B))} -> 2 | C20: {=COUNTA(_xlfn.UNIQUE(_xlfn._xlws.FILTER('TABELA TOTAL'!A:A,'TABELA TOTAL'!E:E=RFM!A20)))} -> 9 | D20: =SUMIF('TABELA TOTAL'!E:E,RFM!A20,'TABELA TOTAL'!G:G) -> 3651.8585 | E20: 5 | F20: 3 | G20: {=_xlfn.IFS(D20<=_xlfn.PERCENTILE.INC(D:D,0.2),1, D20<=_xlfn.PERCENTILE.INC(D:D,0.4),2, D20<=_xlfn.PERCENTILE.INC(D:D,0.6),3, D21<=_xlfn.PERCENTILE.INC(D:D,0.8),4, TRUE,5)} -> 4 | H20: =ROUND(AVERAGE(F20,G20),0) -> 4 | I20: {=INDEX($N$2:$N$26,MATCH(1,($K$2:$K$26=$E20)*($L$2:$L$26=$H20),0))} -> Fiéis | K20: 4 | L20: 4 | M20: B | N20: Fiéis
A21: SV-20935 | B21: {=MAX('TABELA TOTAL'!B:B) - MAX(IF('TABELA TOTAL'!E:E =RFM!A21,'TABELA TOTAL'!B:B))} -> 2 | C21: {=COUNTA(_xlfn.UNIQUE(_xlfn._xlws.FILTER('TABELA TOTAL'!A:A,'TABELA TOTAL'!E:E=RFM!A21)))} -> 8 | D21: =SUMIF('TABELA TOTAL'!E:E,RFM!A21,'TABELA TOTAL'!G:G) -> 1903.491 | E21: 5 | F21: 3 | G21: {=_xlfn.IFS(D21<=_xlfn.PERCENTILE.INC(D:D,0.2),1, D21<=_xlfn.PERCENTILE.INC(D:D,0.4),2, D21<=_xlfn.PERCENTILE.INC(D:D,0.6),3, D22<=_xlfn.PERCENTILE.INC(D:D,0.8),4, TRUE,5)} -> 3 | H21: =ROUND(AVERAGE(F21,G21),0) -> 3 | I21: {=INDEX($N$2:$N$26,MATCH(1,($K$2:$K$26=$E21)*($L$2:$L$26=$H21),0))} -> Fiéis Potencial | K21: 4 | L21: 5 | M21: B | N21: Fiéis
A22: DR-12880 | B22: {=MAX('TABELA TOTAL'!B:B) - MAX(IF('TABELA TOTAL'!E:E =RFM!A22,'TABELA TOTAL'!B:B))} -> 3 | C22: {=COUNTA(_xlfn.UNIQUE(_xlfn._xlws.FILTER('TABELA TOTAL'!A:A,'TABELA TOTAL'!E:E=RFM!A22)))} -> 9 | D22: =SUMIF('TABELA TOTAL'!E:E,RFM!A22,'TABELA TOTAL'!G:G) -> 6528.034 | E22: 5 | F22: 3 | G22: {=_xlfn.IFS(D22<=_xlfn.PERCENTILE.INC(D:D,0.2),1, D22<=_xlfn.PERCENTILE.INC(D:D,0.4),2, D22<=_xlfn.PERCENTILE.INC(D:D,0.6),3, D23<=_xlfn.PERCENTILE.INC(D:D,0.8),4, TRUE,5)} -> 5 | H22: =ROUND(AVERAGE(F22,G22),0) -> 4 | I22: {=INDEX($N$2:$N$26,MATCH(1,($K$2:$K$26=$E22)*($L$2:$L$26=$H22),0))} -> Fiéis | K22: 5 | L22: 1 | M22: D | N22: Novos Clientes
A23: PO-18850 | B23: {=MAX('TABELA TOTAL'!B:B) - MAX(IF('TABELA TOTAL'!E:E =RFM!A23,'TABELA TOTAL'!B:B))} -> 4 | C23: {=COUNTA(_xlfn.UNIQUE(_xlfn._xlws.FILTER('TABELA TOTAL'!A:A,'TABELA TOTAL'!E:E=RFM!A23)))} -> 11 | D23: =SUMIF('TABELA TOTAL'!E:E,RFM!A23,'TABELA TOTAL'!G:G) -> 7473.8282 | E23: 5 | F23: 4 | G23: {=_xlfn.IFS(D23<=_xlfn.PERCENTILE.INC(D:D,0.2),1, D23<=_xlfn.PERCENTILE.INC(D:D,0.4),2, D23<=_xlfn.PERCENTILE.INC(D:D,0.6),3, D24<=_xlfn.PERCENTILE.INC(D:D,0.8),4, TRUE,5)} -> 4 | H23: =ROUND(AVERAGE(F23,G23),0) -> 4 | I23: {=INDEX($N$2:$N$26,MATCH(1,($K$2:$K$26=$E23)*($L$2:$L$26=$H23),0))} -> Fiéis | K23: 5 | L23: 2 | M23: C | N23: Fiéis Potencial
A24: TC-21535 | B24: {=MAX('TABELA TOTAL'!B:B) - MAX(IF('TABELA TOTAL'!E:E =RFM!A24,'TABELA TOTAL'!B:B))} -> 4 | C24: {=COUNTA(_xlfn.UNIQUE(_xlfn._xlws.FILTER('TABELA TOTAL'!A:A,'TABELA TOTAL'!E:E=RFM!A24)))} -> 7 | D24: =SUMIF('TABELA TOTAL'!E:E,RFM!A24,'TABELA TOTAL'!G:G) -> 742.558 | E24: 5 | F24: 3 | G24: {=_xlfn.IFS(D24<=_xlfn.PERCENTILE.INC(D:D,0.2),1, D24<=_xlfn.PERCENTILE.INC(D:D,0.4),2, D24<=_xlfn.PERCENTILE.INC(D:D,0.6),3, D25<=_xlfn.PERCENTILE.INC(D:D,0.8),4, TRUE,5)} -> 1 | H24: =ROUND(AVERAGE(F24,G24),0) -> 2 | I24: {=INDEX($N$2:$N$26,MATCH(1,($K$2:$K$26=$E24)*($L$2:$L$26=$H24),0))} -> Fiéis Potencial | K24: 5 | L24: 3 | M24: C | N24: Fiéis Potencial
A25: YC-21895 | B25: {=MAX('TABELA TOTAL'!B:B) - MAX(IF('TABELA TOTAL'!E:E =RFM!A25,'TABELA TOTAL'!B:B))} -> 4 | C25: {=COUNTA(_xlfn.UNIQUE(_xlfn._xlws.FILTER('TABELA TOTAL'!A:A,'TABELA TOTAL'!E:E=RFM!A25)))} -> 5 | D25: =SUMIF('TABELA TOTAL'!E:E,RFM!A25,'TABELA TOTAL'!G:G) -> 5454.35 | E25: 5 | F25: 2 | G25: {=_xlfn.IFS(D25<=_xlfn.PERCENTILE.INC(D:D,0.2),1, D25<=_xlfn.PERCENTILE.INC(D:D,0.4),2, D25<=_xlfn.PERCENTILE.INC(D:D,0.6),3, D26<=_xlfn.PERCENTILE.INC(D:D,0.8),4, TRUE,5)} -> 4 | H25: =ROUND(AVERAGE(F25,G25),0) -> 3 | I25: {=INDEX($N$2:$N$26,MATCH(1,($K$2:$K$26=$E25)*($L$2:$L$26=$H25),0))} -> Fiéis Potencial | K25: 5 | L25: 4 | M25: B | N25: Fiéis
A26: KB-16240 | B26: {=MAX('TABELA TOTAL'!B:B) - MAX(IF('TABELA TOTAL'!E:E =RFM!A26,'TABELA TOTAL'!B:B))} -> 4 | C26: {=COUNTA(_xlfn.UNIQUE(_xlfn._xlws.FILTER('TABELA TOTAL'!A:A,'TABELA TOTAL'!E:E=RFM!A26)))} -> 7 | D26: =SUMIF('TABELA TOTAL'!E:E,RFM!A26,'TABELA TOTAL'!G:G) -> 3152.615 | E26: 5 | F26: 3 | G26: {=_xlfn.IFS(D26<=_xlfn.PERCENTILE.INC(D:D,0.2),1, D26<=_xlfn.PERCENTILE.INC(D:D,0.4),2, D26<=_xlfn.PERCENTILE.INC(D:D,0.6),3, D27<=_xlfn.PERCENTILE.INC(D:D,0.8),4, TRUE,5)} -> 4 | H26: =ROUND(AVERAGE(F26,G26),0) -> 4 | I26: {=INDEX($N$2:$N$26,MATCH(1,($K$2:$K$26=$E26)*($L$2:$L$26=$H26),0))} -> Fiéis | K26: 5 | L26: 5 | M26: A | N26: Campeão
A27: CV-12805 | B27: {=MAX('TABELA TOTAL'!B:B) - MAX(IF('TABELA TOTAL'!E:E =RFM!A27,'TABELA TOTAL'!B:B))} -> 5 | C27: {=COUNTA(_xlfn.UNIQUE(_xlfn._xlws.FILTER('TABELA TOTAL'!A:A,'TABELA TOTAL'!E:E=RFM!A27)))} -> 9 | D27: =SUMIF('TABELA TOTAL'!E:E,RFM!A27,'TABELA TOTAL'!G:G) -> 2370.3136 | E27: 5 | F27: 3 | G27: {=_xlfn.IFS(D27<=_xlfn.PERCENTILE.INC(D:D,0.2),1, D27<=_xlfn.PERCENTILE.INC(D:D,0.4),2, D27<=_xlfn.PERCENTILE.INC(D:D,0.6),3, D28<=_xlfn.PERCENTILE.INC(D:D,0.8),4, TRUE,5)} -> 3 | H27: =ROUND(AVERAGE(F27,G27),0) -> 3 | I27: {=INDEX($N$2:$N$26,MATCH(1,($K$2:$K$26=$E27)*($L$2:$L$26=$H27),0))} -> Fiéis Potencial
A28: RA-19285 | B28: {=MAX('TABELA TOTAL'!B:B) - MAX(IF('TABELA TOTAL'!E:E =RFM!A28,'TABELA TOTAL'!B:B))} -> 5 | C28: {=COUNTA(_xlfn.UNIQUE(_xlfn._xlws.FILTER('TABELA TOTAL'!A:A,'TABELA TOTAL'!E:E=RFM!A28)))} -> 9 | D28: =SUMIF('TABELA TOTAL'!E:E,RFM!A28,'TABELA TOTAL'!G:G) -> 2617.906 | E28: 5 | F28: 3 | G28: {=_xlfn.IFS(D28<=_xlfn.PERCENTILE.INC(D:D,0.2),1, D28<=_xlfn.PERCENTILE.INC(D:D,0.4),2, D28<=_xlfn.PERCENTILE.INC(D:D,0.6),3, D29<=_xlfn.PERCENTILE.INC(D:D,0.8),4, TRUE,5)} -> 3 | H28: =ROUND(AVERAGE(F28,G28),0) -> 3 | I28: {=INDEX($N$2:$N$26,MATCH(1,($K$2:$K$26=$E28)*($L$2:$L$26=$H28),0))} -> Fiéis Potencial
A29: JW-15955 | B29: {=MAX('TABELA TOTAL'!B:B) - MAX(IF('TABELA TOTAL'!E:E =RFM!A29,'TABELA TOTAL'!B:B))} -> 5 | C29: {=COUNTA(_xlfn.UNIQUE(_xlfn._xlws.FILTER('TABELA TOTAL'!A:A,'TABELA TOTAL'!E:E=RFM!A29)))} -> 7 | D29: =SUMIF('TABELA TOTAL'!E:E,RFM!A29,'TABELA TOTAL'!G:G) -> 1244.086 | E29: 5 | F29: 3 | G29: {=_xlfn.IFS(D29<=_xlfn.PERCENTILE.INC(D:D,0.2),1, D29<=_xlfn.PERCENTILE.INC(D:D,0.4),2, D29<=_xlfn.PERCENTILE.INC(D:D,0.6),3, D30<=_xlfn.PERCENTILE.INC(D:D,0.8),4, TRUE,5)} -> 2 | H29: =ROUND(AVERAGE(F29,G29),0) -> 3 | I29: {=INDEX($N$2:$N$26,MATCH(1,($K$2:$K$26=$E29)*($L$2:$L$26=$H29),0))} -> Fiéis Potencial
A30: MH-18115 | B30: {=MAX('TABELA TOTAL'!B:B) - MAX(IF('TABELA TOTAL'!E:E =RFM!A30,'TABELA TOTAL'!B:B))} -> 5 | C30: {=COUNTA(_xlfn.UNIQUE(_xlfn._xlws.FILTER('TABELA TOTAL'!A:A,'TABELA TOTAL'!E:E=RFM!A30)))} -> 9 | D30: =SUMIF('TABELA TOTAL'!E:E,RFM!A30,'TABELA TOTAL'!G:G) -> 5503.093 | E30: 5 | F30: 3 | G30: {=_xlfn.IFS(D30<=_xlfn.PERCENTILE.INC(D:D,0.2),1, D30<=_xlfn.PERCENTILE.INC(D:D,0.4),2, D30<=_xlfn.PERCENTILE.INC(D:D,0.6),3, D31<=_xlfn.PERCENTILE.INC(D:D,0.8),4, TRUE,5)} -> 5 | H30: =ROUND(AVERAGE(F30,G30),0) -> 4 | I30: {=INDEX($N$2:$N$26,MATCH(1,($K$2:$K$26=$E30)*($L$2:$L$26=$H30),0))} -> Fiéis
A31: FH-14365 | B31: {=MAX('TABELA TOTAL'!B:B) - MAX(IF('TABELA TOTAL'!E:E =RFM!A31,'TABELA TOTAL'!B:B))} -> 5 | C31: {=COUNTA(_xlfn.UNIQUE(_xlfn._xlws.FILTER('TABELA TOTAL'!A:A,'TABELA TOTAL'!E:E=RFM!A31)))} -> 8 | D31: =SUMIF('TABELA TOTAL'!E:E,RFM!A31,'TABELA TOTAL'!G:G) -> 6987.196 | E31: 5 | F31: 3 | G31: {=_xlfn.IFS(D31<=_xlfn.PERCENTILE.INC(D:D,0.2),1, D31<=_xlfn.PERCENTILE.INC(D:D,0.4),2, D31<=_xlfn.PERCENTILE.INC(D:D,0.6),3, D32<=_xlfn.PERCENTILE.INC(D:D,0.8),4, TRUE,5)} -> 4 | H31: =ROUND(AVERAGE(F31,G31),0) -> 4 | I31: {=INDEX($N$2:$N$26,MATCH(1,($K$2:$K$26=$E31)*($L$2:$L$26=$H31),0))} -> Fiéis
A32: GD-14590 | B32: {=MAX('TABELA TOTAL'!B:B) - MAX(IF('TABELA TOTAL'!E:E =RFM!A32,'TABELA TOTAL'!B:B))} -> 5 | C32: {=COUNTA(_xlfn.UNIQUE(_xlfn._xlws.FILTER('TABELA TOTAL'!A:A,'TABELA TOTAL'!E:E=RFM!A32)))} -> 4 | D32: =SUMIF('TABELA TOTAL'!E:E,RFM!A32,'TABELA TOTAL'!G:G) -> 1888.07 | E32: 5 | F32: 2 | G32: {=_xlfn.IFS(D32<=_xlfn.PERCENTILE.INC(D:D,0.2),1, D32<=_xlfn.PERCENTILE.INC(D:D,0.4),2, D32<=_xlfn.PERCENTILE.INC(D:D,0.6),3, D33<=_xlfn.PERCENTILE.INC(D:D,0.8),4, TRUE,5)} -> 3 | H32: =ROUND(AVERAGE(F32,G32),0) -> 3 | I32: {=INDEX($N$2:$N$26,MATCH(1,($K$2:$K$26=$E32)*($L$2:$L$26=$H32),0))} -> Fiéis Potencial
A33: GA-14725 | B33: {=MAX('TABELA TOTAL'!B:B) - MAX(IF('TABELA TOTAL'!E:E =RFM!A33,'TABELA TOTAL'!B:B))} -> 5 | C33: {=COUNTA(_xlfn.UNIQUE(_xlfn._xlws.FILTER('TABELA TOTAL'!A:A,'TABELA TOTAL'!E:E=RFM!A33)))} -> 11 | D33: =SUMIF('TABELA TOTAL'!E:E,RFM!A33,'TABELA TOTAL'!G:G) -> 1398.382 | E33: 5 | F33: 4 | G33: {=_xlfn.IFS(D33<=_xlfn.PERCENTILE.INC(D:D,0.2),1, D33<=_xlfn.PERCENTILE.INC(D:D,0.4),2, D33<=_xlfn.PERCENTILE.INC(D:D,0.6),3, D34<=_xlfn.PERCENTILE.INC(D:D,0.8),4, TRUE,5)} -> 2 | H33: =ROUND(AVERAGE(F33,G33),0) -> 3 | I33: {=INDEX($N$2:$N$26,MATCH(1,($K$2:$K$26=$E33)*($L$2:$L$26=$H33),0))} -> Fiéis Potencial
A34: JH-15430 | B34: {=MAX('TABELA TOTAL'!B:B) - MAX(IF('TABELA TOTAL'!E:E =RFM!A34,'TABELA TOTAL'!B:B))} -> 5 | C34: {=COUNTA(_xlfn.UNIQUE(_xlfn._xlws.FILTER('TABELA TOTAL'!A:A,'TABELA TOTAL'!E:E=RFM!A34)))} -> 4 | D34: =SUMIF('TABELA TOTAL'!E:E,RFM!A34,'TABELA TOTAL'!G:G) -> 309.281 | E34: 5 | F34: 2 | G34: {=_xlfn.IFS(D34<=_xlfn.PERCENTILE.INC(D:D,0.2),1, D34<=_xlfn.PERCENTILE.INC(D:D,0.4),2, D34<=_xlfn.PERCENTILE.INC(D:D,0.6),3, D35<=_xlfn.PERCENTILE.INC(D:D,0.8),4, TRUE,5)} -> 1 | H34: =ROUND(AVERAGE(F34,G34),0) -> 2 | I34: {=INDEX($N$2:$N$26,MATCH(1,($K$2:$K$26=$E34)*($L$2:$L$26=$H34),0))} -> Fiéis Potencial
A35: RF-19840 | B35: {=MAX('TABELA TOTAL'!B:B) - MAX(IF('TABELA TOTAL'!E:E =RFM!A35,'TABELA TOTAL'!B:B))} -> 6 | C35: {=COUNTA(_xlfn.UNIQUE(_xlfn._xlws.FILTER('TABELA TOTAL'!A:A,'TABELA TOTAL'!E:E=RFM!A35)))} -> 8 | D35: =SUMIF('TABELA TOTAL'!E:E,RFM!A35,'TABELA TOTAL'!G:G) -> 945.222 | E35: 5 | F35: 3 | G35: {=_xlfn.IFS(D35<=_xlfn.PERCENTILE.INC(D:D,0.2),1, D35<=_xlfn.PERCENTILE.INC(D:D,0.4),2, D35<=_xlfn.PERCENTILE.INC(D:D,0.6),3, D36<=_xlfn.PERCENTILE.INC(D:D,0.8),4, TRUE,5)} -> 1 | H35: =ROUND(AVERAGE(F35,G35),0) -> 2 | I35: {=INDEX($N$2:$N$26,MATCH(1,($K$2:$K$26=$E35)*($L$2:$L$26=$H35),0))} -> Fiéis Potencial
A36: AR-10540 | B36: {=MAX('TABELA TOTAL'!B:B) - MAX(IF('TABELA TOTAL'!E:E =RFM!A36,'TABELA TOTAL'!B:B))} -> 6 | C36: {=COUNTA(_xlfn.UNIQUE(_xlfn._xlws.FILTER('TABELA TOTAL'!A:A,'TABELA TOTAL'!E:E=RFM!A36)))} -> 6 | D36: =SUMIF('TABELA TOTAL'!E:E,RFM!A36,'TABELA TOTAL'!G:G) -> 6608.448 | E36: 5 | F36: 2 | G36: {=_xlfn.IFS(D36<=_xlfn.PERCENTILE.INC(D:D,0.2),1, D36<=_xlfn.PERCENTILE.INC(D:D,0.4),2, D36<=_xlfn.PERCENTILE.INC(D:D,0.6),3, D37<=_xlfn.PERCENTILE.INC(D:D,0.8),4, TRUE,5)} -> 5 | H36: =ROUND(AVERAGE(F36,G36),0) -> 4 | I36: {=INDEX($N$2:$N$26,MATCH(1,($K$2:$K$26=$E36)*($L$2:$L$26=$H36),0))} -> Fiéis
A37: AH-10210 | B37: {=MAX('TABELA TOTAL'!B:B) - MAX(IF('TABELA TOTAL'!E:E =RFM!A37,'TABELA TOTAL'!B:B))} -> 6 | C37: {=COUNTA(_xlfn.UNIQUE(_xlfn._xlws.FILTER('TABELA TOTAL'!A:A,'TABELA TOTAL'!E:E=RFM!A37)))} -> 9 | D37: =SUMIF('TABELA TOTAL'!E:E,RFM!A37,'TABELA TOTAL'!G:G) -> 4805.344 | E37: 5 | F37: 3 | G37: {=_xlfn.IFS(D37<=_xlfn.PERCENTILE.INC(D:D,0.2),1, D37<=_xlfn.PERCENTILE.INC(D:D,0.4),2, D37<=_xlfn.PERCENTILE.INC(D:D,0.6),3, D38<=_xlfn.PERCENTILE.INC(D:D,0.8),4, TRUE,5)} -> 4 | H37: =ROUND(AVERAGE(F37,G37),0) -> 4 | I37: {=INDEX($N$2:$N$26,MATCH(1,($K$2:$K$26=$E37)*($L$2:$L$26=$H37),0))} -> Fiéis
A38: HG-15025 | B38: {=MAX('TABELA TOTAL'!B:B) - MAX(IF('TABELA TOTAL'!E:E =RFM!A38,'TABELA TOTAL'!B:B))} -> 6 | C38: {=COUNTA(_xlfn.UNIQUE(_xlfn._xlws.FILTER('TABELA TOTAL'!A:A,'TABELA TOTAL'!E:E=RFM!A38)))} -> 7 | D38: =SUMIF('TABELA TOTAL'!E:E,RFM!A38,'TABELA TOTAL'!G:G) -> 3690.284 | E38: 5 | F38: 3 | G38: {=_xlfn.IFS(D38<=_xlfn.PERCENTILE.INC(D:D,0.2),1, D38<=_xlfn.PERCENTILE.INC(D:D,0.4),2, D38<=_xlfn.PERCENTILE.INC(D:D,0.6),3, D39<=_xlfn.PERCENTILE.INC(D:D,0.8),4, TRUE,5)} -> 4 | H38: =ROUND(AVERAGE(F38,G38),0) -> 4 | I38: {=INDEX($N$2:$N$26,MATCH(1,($K$2:$K$26=$E38)*($L$2:$L$26=$H38),0))} -> Fiéis
... A77: DB-13660 | B77: {=MAX('TABELA TOTAL'!B:B) - MAX(IF('TABELA TOTAL'!E:E =RFM!A77,'TABELA TOTAL'!B:B))} -> 12 | C77: {=COUNTA(_xlfn.UNIQUE(_xlfn._xlws.FILTER('TABELA TOTAL'!A:A,'TABELA TOTAL'!E:E=RFM!A77)))} -> 7 | D77: =SUMIF('TABELA TOTAL'!E:E,RFM!A77,'TABELA TOTAL'!G:G) -> 1155.202 | E77: 5 | F77: 3 | G77: {=_xlfn.IFS(D77<=_xlfn.PERCENTILE.INC(D:D,0.2),1, D77<=_xlfn.PERCENTILE.INC(D:D,0.4),2, D77<=_xlfn.PERCENTILE.INC(D:D,0.6),3, D78<=_xlfn.PERCENTILE.INC(D:D,0.8),4, TRUE,5)} -> 2 | H77: =ROUND(AVERAGE(F77,G77),0) -> 3 | I77: {=INDEX($N$2:$N$26,MATCH(1,($K$2:$K$26=$E77)*($L$2:$L$26=$H77),0))} -> Fiéis Potencial
A78: EP-13915 | B78: {=MAX('TABELA TOTAL'!B:B) - MAX(IF('TABELA TOTAL'!E:E =RFM!A78,'TABELA TOTAL'!B:B))} -> 12 | C78: {=COUNTA(_xlfn.UNIQUE(_xlfn._xlws.FILTER('TABELA TOTAL'!A:A,'TABELA TOTAL'!E:E=RFM!A78)))} -> 17 | D78: =SUMIF('TABELA TOTAL'!E:E,RFM!A78,'TABELA TOTAL'!G:G) -> 5478.0608 | E78: 5 | F78: #N/A | G78: {=_xlfn.IFS(D78<=_xlfn.PERCENTILE.INC(D:D,0.2),1, D78<=_xlfn.PERCENTILE.INC(D:D,0.4),2, D78<=_xlfn.PERCENTILE.INC(D:D,0.6),3, D79<=_xlfn.PERCENTILE.INC(D:D,0.8),4, TRUE,5)} -> 4 | H78: =ROUND(AVERAGE(F78,G78),0) -> #N/A | I78: {=INDEX($N$2:$N$26,MATCH(1,($K$2:$K$26=$E78)*($L$2:$L$26=$H78),0))} -> #N/A
A79: AH-10030 | B79: {=MAX('TABELA TOTAL'!B:B) - MAX(IF('TABELA TOTAL'!E:E =RFM!A79,'TABELA TOTAL'!B:B))} -> 12 | C79: {=COUNTA(_xlfn.UNIQUE(_xlfn._xlws.FILTER('TABELA TOTAL'!A:A,'TABELA TOTAL'!E:E=RFM!A79)))} -> 7 | D79: =SUMIF('TABELA TOTAL'!E:E,RFM!A79,'TABELA TOTAL'!G:G) -> 1744.7 | E79: 5 | F79: 3 | G79: {=_xlfn.IFS(D79<=_xlfn.PERCENTILE.INC(D:D,0.2),1, D79<=_xlfn.PERCENTILE.INC(D:D,0.4),2, D79<=_xlfn.PERCENTILE.INC(D:D,0.6),3, D80<=_xlfn.PERCENTILE.INC(D:D,0.8),4, TRUE,5)} -> 3 | H79: =ROUND(AVERAGE(F79,G79),0) -> 3 | I79: {=INDEX($N$2:$N$26,MATCH(1,($K$2:$K$26=$E79)*($L$2:$L$26=$H79),0))} -> Fiéis Potencial
A80: TT-21460 | B80: {=MAX('TABELA TOTAL'!B:B) - MAX(IF('TABELA TOTAL'!E:E =RFM!A80,'TABELA TOTAL'!B:B))} -> 12 | C80: {=COUNTA(_xlfn.UNIQUE(_xlfn._xlws.FILTER('TABELA TOTAL'!A:A,'TABELA TOTAL'!E:E=RFM!A80)))} -> 7 | D80: =SUMIF('TABELA TOTAL'!E:E,RFM!A80,'TABELA TOTAL'!G:G) -> 5364.808 | E80: 5 | F80: 3 | G80: {=_xlfn.IFS(D80<=_xlfn.PERCENTILE.INC(D:D,0.2),1, D80<=_xlfn.PERCENTILE.INC(D:D,0.4),2, D80<=_xlfn.PERCENTILE.INC(D:D,0.6),3, D81<=_xlfn.PERCENTILE.INC(D:D,0.8),4, TRUE,5)} -> 4 | H80: =ROUND(AVERAGE(F80,G80),0) -> 4 | I80: {=INDEX($N$2:$N$26,MATCH(1,($K$2:$K$26=$E80)*($L$2:$L$26=$H80),0))} -> Fiéis
A81: BP-11290 | B81: {=MAX('TABELA TOTAL'!B:B) - MAX(IF('TABELA TOTAL'!E:E =RFM!A81,'TABELA TOTAL'!B:B))} -> 12 | C81: {=COUNTA(_xlfn.UNIQUE(_xlfn._xlws.FILTER('TABELA TOTAL'!A:A,'TABELA TOTAL'!E:E=RFM!A81)))} -> 7 | D81: =SUMIF('TABELA TOTAL'!E:E,RFM!A81,'TABELA TOTAL'!G:G) -> 2475.157 | E81: 5 | F81: 3 | G81: {=_xlfn.IFS(D81<=_xlfn.PERCENTILE.INC(D:D,0.2),1, D81<=_xlfn.PERCENTILE.INC(D:D,0.4),2, D81<=_xlfn.PERCENTILE.INC(D:D,0.6),3, D82<=_xlfn.PERCENTILE.INC(D:D,0.8),4, TRUE,5)} -> 3 | H81: =ROUND(AVERAGE(F81,G81),0) -> 3 | I81: {=INDEX($N$2:$N$26,MATCH(1,($K$2:$K$26=$E81)*($L$2:$L$26=$H81),0))} -> Fiéis Potencial
A82: HE-14800 | B82: {=MAX('TABELA TOTAL'!B:B) - MAX(IF('TABELA TOTAL'!E:E =RFM!A82,'TABELA TOTAL'!B:B))} -> 12 | C82: {=COUNTA(_xlfn.UNIQUE(_xlfn._xlws.FILTER('TABELA TOTAL'!A:A,'TABELA TOTAL'!E:E=RFM!A82)))} -> 4 | D82: =SUMIF('TABELA TOTAL'!E:E,RFM!A82,'TABELA TOTAL'!G:G) -> 883.532 | E82: 5 | F82: 2 | G82: {=_xlfn.IFS(D82<=_xlfn.PERCENTILE.INC(D:D,0.2),1, D82<=_xlfn.PERCENTILE.INC(D:D,0.4),2, D82<=_xlfn.PERCENTILE.INC(D:D,0.6),3, D83<=_xlfn.PERCENTILE.INC(D:D,0.8),4, TRUE,5)} -> 1 | H82: =ROUND(AVERAGE(F82,G82),0) -> 2 | I82: {=INDEX($N$2:$N$26,MATCH(1,($K$2:$K$26=$E82)*($L$2:$L$26=$H82),0))} -> Fiéis Potencial
A83: LC-17140 | B83: {=MAX('TABELA TOTAL'!B:B) - MAX(IF('TABELA TOTAL'!E:E =RFM!A83,'TABELA TOTAL'!B:B))} -> 13 | C83: {=COUNTA(_xlfn.UNIQUE(_xlfn._xlws.FILTER('TABELA TOTAL'!A:A,'TABELA TOTAL'!E:E=RFM!A83)))} -> 9 | D83: =SUMIF('TABELA TOTAL'!E:E,RFM!A83,'TABELA TOTAL'!G:G) -> 2633.582 | E83: 5 | F83: 3 | G83: {=_xlfn.IFS(D83<=_xlfn.PERCENTILE.INC(D:D,0.2),1, D83<=_xlfn.PERCENTILE.INC(D:D,0.4),2, D83<=_xlfn.PERCENTILE.INC(D:D,0.6),3, D84<=_xlfn.PERCENTILE.INC(D:D,0.8),4, TRUE,5)} -> 3 | H83: =ROUND(AVERAGE(F83,G83),0) -> 3 | I83: {=INDEX($N$2:$N$26,MATCH(1,($K$2:$K$26=$E83)*($L$2:$L$26=$H83),0))} -> Fiéis Potencial
A84: HR-14770 | B84: {=MAX('TABELA TOTAL'!B:B) - MAX(IF('TABELA TOTAL'!E:E =RFM!A84,'TABELA TOTAL'!B:B))} -> 13 | C84: {=COUNTA(_xlfn.UNIQUE(_xlfn._xlws.FILTER('TABELA TOTAL'!A:A,'TABELA TOTAL'!E:E=RFM!A84)))} -> 5 | D84: =SUMIF('TABELA TOTAL'!E:E,RFM!A84,'TABELA TOTAL'!G:G) -> 1299.288 | E84: 5 | F84: 2 | G84: {=_xlfn.IFS(D84<=_xlfn.PERCENTILE.INC(D:D,0.2),1, D84<=_xlfn.PERCENTILE.INC(D:D,0.4),2, D84<=_xlfn.PERCENTILE.INC(D:D,0.6),3, D85<=_xlfn.PERCENTILE.INC(D:D,0.8),4, TRUE,5)} -> 2 | H84: =ROUND(AVERAGE(F84,G84),0) -> 2 | I84: {=INDEX($N$2:$N$26,MATCH(1,($K$2:$K$26=$E84)*($L$2:$L$26=$H84),0))} -> Fiéis Potencial
A85: VF-21715 | B85: {=MAX('TABELA TOTAL'!B:B) - MAX(IF('TABELA TOTAL'!E:E =RFM!A85,'TABELA TOTAL'!B:B))} -> 13 | C85: {=COUNTA(_xlfn.UNIQUE(_xlfn._xlws.FILTER('TABELA TOTAL'!A:A,'TABELA TOTAL'!E:E=RFM!A85)))} -> 5 | D85: =SUMIF('TABELA TOTAL'!E:E,RFM!A85,'TABELA TOTAL'!G:G) -> 847.944 | E85: 5 | F85: 2 | G85: {=_xlfn.IFS(D85<=_xlfn.PERCENTILE.INC(D:D,0.2),1, D85<=_xlfn.PERCENTILE.INC(D:D,0.4),2, D85<=_xlfn.PERCENTILE.INC(D:D,0.6),3, D86<=_xlfn.PERCENTILE.INC(D:D,0.8),4, TRUE,5)} -> 1 | H85: =ROUND(AVERAGE(F85,G85),0) -> 2 | I85: {=INDEX($N$2:$N$26,MATCH(1,($K$2:$K$26=$E85)*($L$2:$L$26=$H85),0))} -> Fiéis Potencial
A86: AI-10855 | B86: {=MAX('TABELA TOTAL'!B:B) - MAX(IF('TABELA TOTAL'!E:E =RFM!A86,'TABELA TOTAL'!B:B))} -> 13 | C86: {=COUNTA(_xlfn.UNIQUE(_xlfn._xlws.FILTER('TABELA TOTAL'!A:A,'TABELA TOTAL'!E:E=RFM!A86)))} -> 10 | D86: =SUMIF('TABELA TOTAL'!E:E,RFM!A86,'TABELA TOTAL'!G:G) -> 4375.786 | E86: 5 | F86: 4 | G86: {=_xlfn.IFS(D86<=_xlfn.PERCENTILE.INC(D:D,0.2),1, D86<=_xlfn.PERCENTILE.INC(D:D,0.4),2, D86<=_xlfn.PERCENTILE.INC(D:D,0.6),3, D87<=_xlfn.PERCENTILE.INC(D:D,0.8),4, TRUE,5)} -> 5 | H86: =ROUND(AVERAGE(F86,G86),0) -> 5 | I86: {=INDEX($N$2:$N$26,MATCH(1,($K$2:$K$26=$E86)*($L$2:$L$26=$H86),0))} -> Campeão
A87: GB-14575 | B87: {=MAX('TABELA TOTAL'!B:B) - MAX(IF('TABELA TOTAL'!E:E =RFM!A87,'TABELA TOTAL'!B:B))} -> 13 | C87: {=COUNTA(_xlfn.UNIQUE(_xlfn._xlws.FILTER('TABELA TOTAL'!A:A,'TABELA TOTAL'!E:E=RFM!A87)))} -> 5 | D87: =SUMIF('TABELA TOTAL'!E:E,RFM!A87,'TABELA TOTAL'!G:G) -> 4716.288 | E87: 5 | F87: 2 | G87: {=_xlfn.IFS(D87<=_xlfn.PERCENTILE.INC(D:D,0.2),1, D87<=_xlfn.PERCENTILE.INC(D:D,0.4),2, D87<=_xlfn.PERCENTILE.INC(D:D,0.6),3, D88<=_xlfn.PERCENTILE.INC(D:D,0.8),4, TRUE,5)} -> 4 | H87: =ROUND(AVERAGE(F87,G87),0) -> 3 | I87: {=INDEX($N$2:$N$26,MATCH(1,($K$2:$K$26=$E87)*($L$2:$L$26=$H87),0))} -> Fiéis Potencial
A88: CA-12310 | B88: {=MAX('TABELA TOTAL'!B:B) - MAX(IF('TABELA TOTAL'!E:E =RFM!A88,'TABELA TOTAL'!B:B))} -> 13 | C88: {=COUNTA(_xlfn.UNIQUE(_xlfn._xlws.FILTER('TABELA TOTAL'!A:A,'TABELA TOTAL'!E:E=RFM!A88)))} -> 4 | D88: =SUMIF('TABELA TOTAL'!E:E,RFM!A88,'TABELA TOTAL'!G:G) -> 1421.954 | E88: 5 | F88: 2 | G88: {=_xlfn.IFS(D88<=_xlfn.PERCENTILE.INC(D:D,0.2),1, D88<=_xlfn.PERCENTILE.INC(D:D,0.4),2, D88<=_xlfn.PERCENTILE.INC(D:D,0.6),3, D89<=_xlfn.PERCENTILE.INC(D:D,0.8),4, TRUE,5)} -> 2 | H88: =ROUND(AVERAGE(F88,G88),0) -> 2 | I88: {=INDEX($N$2:$N$26,MATCH(1,($K$2:$K$26=$E88)*($L$2:$L$26=$H88),0))} -> Fiéis Potencial
A89: AT-10735 | B89: {=MAX('TABELA TOTAL'!B:B) - MAX(IF('TABELA TOTAL'!E:E =RFM!A89,'TABELA TOTAL'!B:B))} -> 13 | C89: {=COUNTA(_xlfn.UNIQUE(_xlfn._xlws.FILTER('TABELA TOTAL'!A:A,'TABELA TOTAL'!E:E=RFM!A89)))} -> 10 | D89: =SUMIF('TABELA TOTAL'!E:E,RFM!A89,'TABELA TOTAL'!G:G) -> 3831.864 | E89: 5 | F89: 4 | G89: {=_xlfn.IFS(D89<=_xlfn.PERCENTILE.INC(D:D,0.2),1, D89<=_xlfn.PERCENTILE.INC(D:D,0.4),2, D89<=_xlfn.PERCENTILE.INC(D:D,0.6),3, D90<=_xlfn.PERCENTILE.INC(D:D,0.8),4, TRUE,5)} -> 4 | H89: =ROUND(AVERAGE(F89,G89),0) -> 4 | I89: {=INDEX($N$2:$N$26,MATCH(1,($K$2:$K$26=$E89)*($L$2:$L$26=$H89),0))} -> Fiéis
A90: AY-10555 | B90: {=MAX('TABELA TOTAL'!B:B) - MAX(IF('TABELA TOTAL'!E:E =RFM!A90,'TABELA TOTAL'!B:B))} -> 14 | C90: {=COUNTA(_xlfn.UNIQUE(_xlfn._xlws.FILTER('TABELA TOTAL'!A:A,'TABELA TOTAL'!E:E=RFM!A90)))} -> 4 | D90: =SUMIF('TABELA TOTAL'!E:E,RFM!A90,'TABELA TOTAL'!G:G) -> 497.014 | E90: 5 | F90: 2 | G90: {=_xlfn.IFS(D90<=_xlfn.PERCENTILE.INC(D:D,0.2),1, D90<=_xlfn.PERCENTILE.INC(D:D,0.4),2, D90<=_xlfn.PERCENTILE.INC(D:D,0.6),3, D91<=_xlfn.PERCENTILE.INC(D:D,0.8),4, TRUE,5)} -> 1 | H90: =ROUND(AVERAGE(F90,G90),0) -> 2 | I90: {=INDEX($N$2:$N$26,MATCH(1,($K$2:$K$26=$E90)*($L$2:$L$26=$H90),0))} -> Fiéis Potencial
... A695: CJ-11875 | B695: {=MAX('TABELA TOTAL'!B:B) - MAX(IF('TABELA TOTAL'!E:E =RFM!A695,'TABELA TOTAL'!B:B))} -> 365 | C695: {=COUNTA(_xlfn.UNIQUE(_xlfn._xlws.FILTER('TABELA TOTAL'!A:A,'TABELA TOTAL'!E:E=RFM!A695)))} -> 1 | D695: =SUMIF('TABELA TOTAL'!E:E,RFM!A695,'TABELA TOTAL'!G:G) -> 16.52 | E695: 1 | F695: 1 | G695: {=_xlfn.IFS(D695<=_xlfn.PERCENTILE.INC(D:D,0.2),1, D695<=_xlfn.PERCENTILE.INC(D:D,0.4),2, D695<=_xlfn.PERCENTILE.INC(D:D,0.6),3, D696<=_xlfn.PERCENTILE.INC(D:D,0.8),4, TRUE,5)} -> 1 | H695: =ROUND(AVERAGE(F695,G695),0) -> 1 | I695: {=INDEX($N$2:$N$26,MATCH(1,($K$2:$K$26=$E695)*($L$2:$L$26=$H695),0))} -> Perdidos
A696: RC-19825 | B696: {=MAX('TABELA TOTAL'!B:B) - MAX(IF('TABELA TOTAL'!E:E =RFM!A696,'TABELA TOTAL'!B:B))} -> 369 | C696: {=COUNTA(_xlfn.UNIQUE(_xlfn._xlws.FILTER('TABELA TOTAL'!A:A,'TABELA TOTAL'!E:E=RFM!A696)))} -> 6 | D696: =SUMIF('TABELA TOTAL'!E:E,RFM!A696,'TABELA TOTAL'!G:G) -> 966.409 | E696: #N/A | F696: 2 | G696: {=_xlfn.IFS(D696<=_xlfn.PERCENTILE.INC(D:D,0.2),1, D696<=_xlfn.PERCENTILE.INC(D:D,0.4),2, D696<=_xlfn.PERCENTILE.INC(D:D,0.6),3, D697<=_xlfn.PERCENTILE.INC(D:D,0.8),4, TRUE,5)} -> 2 | H696: =ROUND(AVERAGE(F696,G696),0) -> 2 | I696: {=INDEX($N$2:$N$26,MATCH(1,($K$2:$K$26=$E696)*($L$2:$L$26=$H696),0))} -> #N/A
A697: MC-18130 | B697: {=MAX('TABELA TOTAL'!B:B) - MAX(IF('TABELA TOTAL'!E:E =RFM!A697,'TABELA TOTAL'!B:B))} -> 369 | C697: {=COUNTA(_xlfn.UNIQUE(_xlfn._xlws.FILTER('TABELA TOTAL'!A:A,'TABELA TOTAL'!E:E=RFM!A697)))} -> 5 | D697: =SUMIF('TABELA TOTAL'!E:E,RFM!A697,'TABELA TOTAL'!G:G) -> 1581.998 | E697: #N/A | F697: 2 | G697: {=_xlfn.IFS(D697<=_xlfn.PERCENTILE.INC(D:D,0.2),1, D697<=_xlfn.PERCENTILE.INC(D:D,0.4),2, D697<=_xlfn.PERCENTILE.INC(D:D,0.6),3, D698<=_xlfn.PERCENTILE.INC(D:D,0.8),4, TRUE,5)} -> 2 | H697: =ROUND(AVERAGE(F697,G697),0) -> 2 | I697: {=INDEX($N$2:$N$26,MATCH(1,($K$2:$K$26=$E697)*($L$2:$L$26=$H697),0))} -> #N/A
A698: MH-17440 | B698: {=MAX('TABELA TOTAL'!B:B) - MAX(IF('TABELA TOTAL'!E:E =RFM!A698,'TABELA TOTAL'!B:B))} -> 376 | C698: {=COUNTA(_xlfn.UNIQUE(_xlfn._xlws.FILTER('TABELA TOTAL'!A:A,'TABELA TOTAL'!E:E=RFM!A698)))} -> 4 | D698: =SUMIF('TABELA TOTAL'!E:E,RFM!A698,'TABELA TOTAL'!G:G) -> 400.016 | E698: #N/A | F698: 2 | G698: {=_xlfn.IFS(D698<=_xlfn.PERCENTILE.INC(D:D,0.2),1, D698<=_xlfn.PERCENTILE.INC(D:D,0.4),2, D698<=_xlfn.PERCENTILE.INC(D:D,0.6),3, D699<=_xlfn.PERCENTILE.INC(D:D,0.8),4, TRUE,5)} -> 1 | H698: =ROUND(AVERAGE(F698,G698),0) -> 2 | I698: {=INDEX($N$2:$N$26,MATCH(1,($K$2:$K$26=$E698)*($L$2:$L$26=$H698),0))} -> #N/A
A699: LH-17155 | B699: {=MAX('TABELA TOTAL'!B:B) - MAX(IF('TABELA TOTAL'!E:E =RFM!A699,'TABELA TOTAL'!B:B))} -> 385 | C699: {=COUNTA(_xlfn.UNIQUE(_xlfn._xlws.FILTER('TABELA TOTAL'!A:A,'TABELA TOTAL'!E:E=RFM!A699)))} -> 9 | D699: =SUMIF('TABELA TOTAL'!E:E,RFM!A699,'TABELA TOTAL'!G:G) -> 1739.689 | E699: #N/A | F699: 3 | G699: {=_xlfn.IFS(D699<=_xlfn.PERCENTILE.INC(D:D,0.2),1, D699<=_xlfn.PERCENTILE.INC(D:D,0.4),2, D699<=_xlfn.PERCENTILE.INC(D:D,0.6),3, D700<=_xlfn.PERCENTILE.INC(D:D,0.8),4, TRUE,5)} -> 3 | H699: =ROUND(AVERAGE(F699,G699),0) -> 3 | I699: {=INDEX($N$2:$N$26,MATCH(1,($K$2:$K$26=$E699)*($L$2:$L$26=$H699),0))} -> #N/A
A700: CM-12235 | B700: {=MAX('TABELA TOTAL'!B:B) - MAX(IF('TABELA TOTAL'!E:E =RFM!A700,'TABELA TOTAL'!B:B))} -> 385 | C700: {=COUNTA(_xlfn.UNIQUE(_xlfn._xlws.FILTER('TABELA TOTAL'!A:A,'TABELA TOTAL'!E:E=RFM!A700)))} -> 5 | D700: =SUMIF('TABELA TOTAL'!E:E,RFM!A700,'TABELA TOTAL'!G:G) -> 2305.712 | E700: #N/A | F700: 2 | G700: {=_xlfn.IFS(D700<=_xlfn.PERCENTILE.INC(D:D,0.2),1, D700<=_xlfn.PERCENTILE.INC(D:D,0.4),2, D700<=_xlfn.PERCENTILE.INC(D:D,0.6),3, D701<=_xlfn.PERCENTILE.INC(D:D,0.8),4, TRUE,5)} -> 3 | H700: =ROUND(AVERAGE(F700,G700),0) -> 3 | I700: {=INDEX($N$2:$N$26,MATCH(1,($K$2:$K$26=$E700)*($L$2:$L$26=$H700),0))} -> #N/A
A701: SP-20650 | B701: {=MAX('TABELA TOTAL'!B:B) - MAX(IF('TABELA TOTAL'!E:E =RFM!A701,'TABELA TOTAL'!B:B))} -> 386 | C701: {=COUNTA(_xlfn.UNIQUE(_xlfn._xlws.FILTER('TABELA TOTAL'!A:A,'TABELA TOTAL'!E:E=RFM!A701)))} -> 9 | D701: =SUMIF('TABELA TOTAL'!E:E,RFM!A701,'TABELA TOTAL'!G:G) -> 1872.436 | E701: #N/A | F701: 3 | G701: {=_xlfn.IFS(D701<=_xlfn.PERCENTILE.INC(D:D,0.2),1, D701<=_xlfn.PERCENTILE.INC(D:D,0.4),2, D701<=_xlfn.PERCENTILE.INC(D:D,0.6),3, D702<=_xlfn.PERCENTILE.INC(D:D,0.8),4, TRUE,5)} -> 3 | H701: =ROUND(AVERAGE(F701,G701),0) -> 3 | I701: {=INDEX($N$2:$N$26,MATCH(1,($K$2:$K$26=$E701)*($L$2:$L$26=$H701),0))} -> #N/A
A702: PM-18940 | B702: {=MAX('TABELA TOTAL'!B:B) - MAX(IF('TABELA TOTAL'!E:E =RFM!A702,'TABELA TOTAL'!B:B))} -> 386 | C702: {=COUNTA(_xlfn.UNIQUE(_xlfn._xlws.FILTER('TABELA TOTAL'!A:A,'TABELA TOTAL'!E:E=RFM!A702)))} -> 3 | D702: =SUMIF('TABELA TOTAL'!E:E,RFM!A702,'TABELA TOTAL'!G:G) -> 1405.402 | E702: #N/A | F702: 1 | G702: {=_xlfn.IFS(D702<=_xlfn.PERCENTILE.INC(D:D,0.2),1, D702<=_xlfn.PERCENTILE.INC(D:D,0.4),2, D702<=_xlfn.PERCENTILE.INC(D:D,0.6),3, D703<=_xlfn.PERCENTILE.INC(D:D,0.8),4, TRUE,5)} -> 2 | H702: =ROUND(AVERAGE(F702,G702),0) -> 2 | I702: {=INDEX($N$2:$N$26,MATCH(1,($K$2:$K$26=$E702)*($L$2:$L$26=$H702),0))} -> #N/A
A703: GH-14485 | B703: {=MAX('TABELA TOTAL'!B:B) - MAX(IF('TABELA TOTAL'!E:E =RFM!A703,'TABELA TOTAL'!B:B))} -> 387 | C703: {=COUNTA(_xlfn.UNIQUE(_xlfn._xlws.FILTER('TABELA TOTAL'!A:A,'TABELA TOTAL'!E:E=RFM!A703)))} -> 2 | D703: =SUMIF('TABELA TOTAL'!E:E,RFM!A703,'TABELA TOTAL'!G:G) -> 1361.244 | E703: #N/A | F703: 1 | G703: {=_xlfn.IFS(D703<=_xlfn.PERCENTILE.INC(D:D,0.2),1, D703<=_xlfn.PERCENTILE.INC(D:D,0.4),2, D703<=_xlfn.PERCENTILE.INC(D:D,0.6),3, D704<=_xlfn.PERCENTILE.INC(D:D,0.8),4, TRUE,5)} -> 2 | H703: =ROUND(AVERAGE(F703,G703),0) -> 2 | I703: {=INDEX($N$2:$N$26,MATCH(1,($K$2:$K$26=$E703)*($L$2:$L$26=$H703),0))} -> #N/A
A704: IM-15070 | B704: {=MAX('TABELA TOTAL'!B:B) - MAX(IF('TABELA TOTAL'!E:E =RFM!A704,'TABELA TOTAL'!B:B))} -> 390 | C704: {=COUNTA(_xlfn.UNIQUE(_xlfn._xlws.FILTER('TABELA TOTAL'!A:A,'TABELA TOTAL'!E:E=RFM!A704)))} -> 7 | D704: =SUMIF('TABELA TOTAL'!E:E,RFM!A704,'TABELA TOTAL'!G:G) -> 4930.474 | E704: #N/A | F704: 3 | G704: {=_xlfn.IFS(D704<=_xlfn.PERCENTILE.INC(D:D,0.2),1, D704<=_xlfn.PERCENTILE.INC(D:D,0.4),2, D704<=_xlfn.PERCENTILE.INC(D:D,0.6),3, D705<=_xlfn.PERCENTILE.INC(D:D,0.8),4, TRUE,5)} -> 4 | H704: =ROUND(AVERAGE(F704,G704),0) -> 4 | I704: {=INDEX($N$2:$N$26,MATCH(1,($K$2:$K$26=$E704)*($L$2:$L$26=$H704),0))} -> #N/A
A705: RF-19345 | B705: {=MAX('TABELA TOTAL'!B:B) - MAX(IF('TABELA TOTAL'!E:E =RFM!A705,'TABELA TOTAL'!B:B))} -> 390 | C705: {=COUNTA(_xlfn.UNIQUE(_xlfn._xlws.FILTER('TABELA TOTAL'!A:A,'TABELA TOTAL'!E:E=RFM!A705)))} -> 8 | D705: =SUMIF('TABELA TOTAL'!E:E,RFM!A705,'TABELA TOTAL'!G:G) -> 3309.15 | E705: #N/A | F705: 3 | G705: {=_xlfn.IFS(D705<=_xlfn.PERCENTILE.INC(D:D,0.2),1, D705<=_xlfn.PERCENTILE.INC(D:D,0.4),2, D705<=_xlfn.PERCENTILE.INC(D:D,0.6),3, D706<=_xlfn.PERCENTILE.INC(D:D,0.8),4, TRUE,5)} -> 4 | H705: =ROUND(AVERAGE(F705,G705),0) -> 4 | I705: {=INDEX($N$2:$N$26,MATCH(1,($K$2:$K$26=$E705)*($L$2:$L$26=$H705),0))} -> #N/A
A706: LM-17065 | B706: {=MAX('TABELA TOTAL'!B:B) - MAX(IF('TABELA TOTAL'!E:E =RFM!A706,'TABELA TOTAL'!B:B))} -> 391 | C706: {=COUNTA(_xlfn.UNIQUE(_xlfn._xlws.FILTER('TABELA TOTAL'!A:A,'TABELA TOTAL'!E:E=RFM!A706)))} -> 5 | D706: =SUMIF('TABELA TOTAL'!E:E,RFM!A706,'TABELA TOTAL'!G:G) -> 1346.774 | E706: #N/A | F706: 2 | G706: {=_xlfn.IFS(D706<=_xlfn.PERCENTILE.INC(D:D,0.2),1, D706<=_xlfn.PERCENTILE.INC(D:D,0.4),2, D706<=_xlfn.PERCENTILE.INC(D:D,0.6),3, D707<=_xlfn.PERCENTILE.INC(D:D,0.8),4, TRUE,5)} -> 2 | H706: =ROUND(AVERAGE(F706,G706),0) -> 2 | I706: {=INDEX($N$2:$N$26,MATCH(1,($K$2:$K$26=$E706)*($L$2:$L$26=$H706),0))} -> #N/A
A707: KT-16465 | B707: {=MAX('TABELA TOTAL'!B:B) - MAX(IF('TABELA TOTAL'!E:E =RFM!A707,'TABELA TOTAL'!B:B))} -> 391 | C707: {=COUNTA(_xlfn.UNIQUE(_xlfn._xlws.FILTER('TABELA TOTAL'!A:A,'TABELA TOTAL'!E:E=RFM!A707)))} -> 7 | D707: =SUMIF('TABELA TOTAL'!E:E,RFM!A707,'TABELA TOTAL'!G:G) -> 3057.1 | E707: #N/A | F707: 3 | G707: {=_xlfn.IFS(D707<=_xlfn.PERCENTILE.INC(D:D,0.2),1, D707<=_xlfn.PERCENTILE.INC(D:D,0.4),2, D707<=_xlfn.PERCENTILE.INC(D:D,0.6),3, D708<=_xlfn.PERCENTILE.INC(D:D,0.8),4, TRUE,5)} -> 5 | H707: =ROUND(AVERAGE(F707,G707),0) -> 4 | I707: {=INDEX($N$2:$N$26,MATCH(1,($K$2:$K$26=$E707)*($L$2:$L$26=$H707),0))} -> #N/A
... A794: NB-18580 | B794: {=MAX('TABELA TOTAL'!B:B) - MAX(IF('TABELA TOTAL'!E:E =RFM!A794,'TABELA TOTAL'!B:B))} -> 1165 | C794: {=COUNTA(_xlfn.UNIQUE(_xlfn._xlws.FILTER('TABELA TOTAL'!A:A,'TABELA TOTAL'!E:E=RFM!A794)))} -> 2 | D794: =SUMIF('TABELA TOTAL'!E:E,RFM!A794,'TABELA TOTAL'!G:G) -> 273.872 | E794: #N/A | F794: 1 | G794: {=_xlfn.IFS(D794<=_xlfn.PERCENTILE.INC(D:D,0.2),1, D794<=_xlfn.PERCENTILE.INC(D:D,0.4),2, D794<=_xlfn.PERCENTILE.INC(D:D,0.6),3, D795<=_xlfn.PERCENTILE.INC(D:D,0.8),4, TRUE,5)} -> 1 | H794: =ROUND(AVERAGE(F794,G794),0) -> 1 | I794: {=INDEX($N$2:$N$26,MATCH(1,($K$2:$K$26=$E794)*($L$2:$L$26=$H794),0))} -> #N/A
A795: 0 | B795: {=MAX('TABELA TOTAL'!B:B) - MAX(IF('TABELA TOTAL'!E:E =RFM!A795,'TABELA TOTAL'!B:B))} -> 43099 | C795: {=COUNTA(_xlfn.UNIQUE(_xlfn._xlws.FILTER('TABELA TOTAL'!A:A,'TABELA TOTAL'!E:E=RFM!A795)))} -> 1 | D795: =SUMIF('TABELA TOTAL'!E:E,RFM!A795,'TABELA TOTAL'!G:G) -> 0 | E795: #N/A | F795: 1 | G795: {=_xlfn.IFS(D795<=_xlfn.PERCENTILE.INC(D:D,0.2),1, D795<=_xlfn.PERCENTILE.INC(D:D,0.4),2, D795<=_xlfn.PERCENTILE.INC(D:D,0.6),3, D796<=_xlfn.PERCENTILE.INC(D:D,0.8),4, TRUE,5)} -> 1 | H795: =ROUND(AVERAGE(F795,G795),0) -> 1 | I795: {=INDEX($N$2:$N$26,MATCH(1,($K$2:$K$26=$E795)*($L$2:$L$26=$H795),0))} -> #N/A
E796: #N/A | G796: {=_xlfn.IFS(D796<=_xlfn.PERCENTILE.INC(D:D,0.2),1, D796<=_xlfn.PERCENTILE.INC(D:D,0.4),2, D796<=_xlfn.PERCENTILE.INC(D:D,0.6),3, D797<=_xlfn.PERCENTILE.INC(D:D,0.8),4, TRUE,5)} -> 1 | H796: =ROUND(AVERAGE(F796,G796),0) -> 1 | I796: {=INDEX($N$2:$N$26,MATCH(1,($K$2:$K$26=$E796)*($L$2:$L$26=$H796),0))} -> #N/A
E797: #N/A | G797: {=_xlfn.IFS(D797<=_xlfn.PERCENTILE.INC(D:D,0.2),1, D797<=_xlfn.PERCENTILE.INC(D:D,0.4),2, D797<=_xlfn.PERCENTILE.INC(D:D,0.6),3, D798<=_xlfn.PERCENTILE.INC(D:D,0.8),4, TRUE,5)} -> 1 | H797: =ROUND(AVERAGE(F797,G797),0) -> 1 | I797: {=INDEX($N$2:$N$26,MATCH(1,($K$2:$K$26=$E797)*($L$2:$L$26=$H797),0))} -> #N/A
E798: #N/A | G798: {=_xlfn.IFS(D798<=_xlfn.PERCENTILE.INC(D:D,0.2),1, D798<=_xlfn.PERCENTILE.INC(D:D,0.4),2, D798<=_xlfn.PERCENTILE.INC(D:D,0.6),3, D799<=_xlfn.PERCENTILE.INC(D:D,0.8),4, TRUE,5)} -> 1 | H798: =ROUND(AVERAGE(F798,G798),0) -> 1 | I798: {=INDEX($N$2:$N$26,MATCH(1,($K$2:$K$26=$E798)*($L$2:$L$26=$H798),0))} -> #N/A
E799: #N/A | G799: {=_xlfn.IFS(D799<=_xlfn.PERCENTILE.INC(D:D,0.2),1, D799<=_xlfn.PERCENTILE.INC(D:D,0.4),2, D799<=_xlfn.PERCENTILE.INC(D:D,0.6),3, D800<=_xlfn.PERCENTILE.INC(D:D,0.8),4, TRUE,5)} -> 1 | H799: =ROUND(AVERAGE(F799,G799),0) -> 1 | I799: {=INDEX($N$2:$N$26,MATCH(1,($K$2:$K$26=$E799)*($L$2:$L$26=$H799),0))} -> #N/A
E800: #N/A | G800: {=_xlfn.IFS(D800<=_xlfn.PERCENTILE.INC(D:D,0.2),1, D800<=_xlfn.PERCENTILE.INC(D:D,0.4),2, D800<=_xlfn.PERCENTILE.INC(D:D,0.6),3, D801<=_xlfn.PERCENTILE.INC(D:D,0.8),4, TRUE,5)} -> 1 | H800: =ROUND(AVERAGE(F800,G800),0) -> 1 | I800: {=INDEX($N$2:$N$26,MATCH(1,($K$2:$K$26=$E800)*($L$2:$L$26=$H800),0))} -> #N/A
E801: #N/A | G801: {=_xlfn.IFS(D801<=_xlfn.PERCENTILE.INC(D:D,0.2),1, D801<=_xlfn.PERCENTILE.INC(D:D,0.4),2, D801<=_xlfn.PERCENTILE.INC(D:D,0.6),3, D802<=_xlfn.PERCENTILE.INC(D:D,0.8),4, TRUE,5)} -> 1 | H801: =ROUND(AVERAGE(F801,G801),0) -> 1 | I801: {=INDEX($N$2:$N$26,MATCH(1,($K$2:$K$26=$E801)*($L$2:$L$26=$H801),0))} -> #N/A
E802: #N/A | G802: {=_xlfn.IFS(D802<=_xlfn.PERCENTILE.INC(D:D,0.2),1, D802<=_xlfn.PERCENTILE.INC(D:D,0.4),2, D802<=_xlfn.PERCENTILE.INC(D:D,0.6),3, D803<=_xlfn.PERCENTILE.INC(D:D,0.8),4, TRUE,5)} -> 1 | H802: =ROUND(AVERAGE(F802,G802),0) -> 1 | I802: {=INDEX($N$2:$N$26,MATCH(1,($K$2:$K$26=$E802)*($L$2:$L$26=$H802),0))} -> #N/A
E803: #N/A | G803: {=_xlfn.IFS(D803<=_xlfn.PERCENTILE.INC(D:D,0.2),1, D803<=_xlfn.PERCENTILE.INC(D:D,0.4),2, D803<=_xlfn.PERCENTILE.INC(D:D,0.6),3, D804<=_xlfn.PERCENTILE.INC(D:D,0.8),4, TRUE,5)} -> 1 | H803: =ROUND(AVERAGE(F803,G803),0) -> 1 | I803: {=INDEX($N$2:$N$26,MATCH(1,($K$2:$K$26=$E803)*($L$2:$L$26=$H803),0))} -> #N/A
E804: #N/A | G804: {=_xlfn.IFS(D804<=_xlfn.PERCENTILE.INC(D:D,0.2),1, D804<=_xlfn.PERCENTILE.INC(D:D,0.4),2, D804<=_xlfn.PERCENTILE.INC(D:D,0.6),3, D805<=_xlfn.PERCENTILE.INC(D:D,0.8),4, TRUE,5)} -> 1 | H804: =ROUND(AVERAGE(F804,G804),0) -> 1 | I804: {=INDEX($N$2:$N$26,MATCH(1,($K$2:$K$26=$E804)*($L$2:$L$26=$H804),0))} -> #N/A
E805: #N/A | G805: {=_xlfn.IFS(D805<=_xlfn.PERCENTILE.INC(D:D,0.2),1, D805<=_xlfn.PERCENTILE.INC(D:D,0.4),2, D805<=_xlfn.PERCENTILE.INC(D:D,0.6),3, D806<=_xlfn.PERCENTILE.INC(D:D,0.8),4, TRUE,5)} -> 1 | H805: =ROUND(AVERAGE(F805,G805),0) -> 1 | I805: {=INDEX($N$2:$N$26,MATCH(1,($K$2:$K$26=$E805)*($L$2:$L$26=$H805),0))} -> #N/A
E806: #N/A | G806: {=_xlfn.IFS(D806<=_xlfn.PERCENTILE.INC(D:D,0.2),1, D806<=_xlfn.PERCENTILE.INC(D:D,0.4),2, D806<=_xlfn.PERCENTILE.INC(D:D,0.6),3, D807<=_xlfn.PERCENTILE.INC(D:D,0.8),4, TRUE,5)} -> 1 | H806: =ROUND(AVERAGE(F806,G806),0) -> 1 | I806: {=INDEX($N$2:$N$26,MATCH(1,($K$2:$K$26=$E806)*($L$2:$L$26=$H806),0))} -> #N/A
E807: #N/A | G807: {=_xlfn.IFS(D807<=_xlfn.PERCENTILE.INC(D:D,0.2),1, D807<=_xlfn.PERCENTILE.INC(D:D,0.4),2, D807<=_xlfn.PERCENTILE.INC(D:D,0.6),3, D808<=_xlfn.PERCENTILE.INC(D:D,0.8),4, TRUE,5)} -> 1 | H807: =ROUND(AVERAGE(F807,G807),0) -> 1 | I807: {=INDEX($N$2:$N$26,MATCH(1,($K$2:$K$26=$E807)*($L$2:$L$26=$H807),0))} -> #N/A
... E2764: #N/A | G2764: {=_xlfn.IFS(D2764<=_xlfn.PERCENTILE.INC(D:D,0.2),1, D2764<=_xlfn.PERCENTILE.INC(D:D,0.4),2, D2764<=_xlfn.PERCENTILE.INC(D:D,0.6),3, D2765<=_xlfn.PERCENTILE.INC(D:D,0.8),4, TRUE,5)} -> 1 | H2764: =ROUND(AVERAGE(F2764,G2764),0) -> 1 | I2764: {=INDEX($N$2:$N$26,MATCH(1,($K$2:$K$26=$E2764)*($L$2:$L$26=$H2764),0))} -> #N/A
E2765: #N/A
E2766: #N/A
E2767: #N/A
E2768: #N/A
E2769: #N/A
E2770: #N/A
E2771: #N/A
E2772: #N/A
E2773: #N/A
E2774: #N/A
E2775: #N/A
E2776: #N/A
... E7945: #N/A
